Workbook
Name TaxaCompra: Config!$B$4
Name TaxaVenda: Config!$B$5
Name RetRefino: Config!$B$6
Name RetCraft: Config!$B$7
Name FeeRefino: Config!$B$8
Name FeeCraft: Config!$B$9

Sheet Config
A1: Configurações gerais
A2: Células amarelas = você preenche. Tudo na planilha obedece a esta tela.
A3: Parâmetro | B3: Valor | C3: Como usar
A4: Taxa de compra (ordem de compra) | B4: 0 | C4: 0% se comprar direto da oferta; 2,5% se criar ordem de compra.
A5: Taxa total de venda | B5: 0.065 | C5: 6,5% com Premium (4% imposto + 2,5% ordem de venda); 10,5% sem Premium.
A6: Retorno de recursos no REFINO | B6: 0.367 | C6: Ex.: 36,7% (cidade com bônus) ou 53,9% com foco. Use o valor da sua situação.
A7: Retorno de recursos no CRAFT | B7: 0.248 | C7: Ex.: 24,8% (cidade com bônus de placas), 15,2% sem bônus, ~47,9% com foco.
A8: Taxa da barraca - Refino (prata/100 nutrição) | B8: 465 | C8: Taxa mostrada na fundição. Usada em: Valor do item x 0,1125 x taxa / 100.
A9: Taxa da barraca - Craft (prata/100 nutrição) | B9: 465 | C9: Taxa mostrada na forja de armaduras.
A12: Como usar a planilha
A13: 1) Preencha os preços de COMPRA nas abas Minerio, Barras e Artefatos (5 cidades). Deixe em branco o que não encontrou.
A14: 2) Aba Refino: a planilha compara refinar x comprar a barra pronta e escolhe a mais barata. Para forçar, mude a coluna 'Origem' (Automático / Comprar / Refinar).
A15: 3) Aba Itens: preencha os preços de VENDA das peças (5 cidades + Caerleon + Mercado Negro). Ela calcula custo, lucro e margem de TODAS as combinações; use o filtro para ordenar.
A16: 4) Aba Craft: escolha Variante, Peça, Tier (T4.0 ... T8.4) e a quantidade. Veja custo, melhor local de venda, lucro unitário e total.
A17: 5) Aba Lista_Compras: mostra o que comprar (barras, minérios e artefatos), em qual cidade e quanto isso custa.
A18: Observações: artefatos NÃO retornam no craft (confirmado nos dados do jogo). A taxa da barraca não é devolvida pelo retorno de recursos.
A19: Quantidades da Lista_Compras são líquidas (já descontado o retorno de recursos esperado).

Sheet Craft
A1: Planejador de craft - Placas (armadura, elmo, botas)
A2: Escolha nas células amarelas (listas suspensas). Cada linha = um tipo de peça que você quer craftar.
A3: LUCRO TOTAL ESPERADO: | D3: =SUM(Q6:Q35) | F3: CUSTO TOTAL DO LOTE: | I3: =SUM(R6:R35)
A5: Variante | B5: Peça | C5: Tier | D5: Qtd a craftar | E5: Linha em Itens | F5: Barras por peça | G5: Custo barras (líq. retorno) | H5: Artefato (preço) | I5: Cidade do artefato | J5: Taxa do ferreiro | K5: CUSTO TOTAL / peça | L5: Melhor preço de venda | M5: Melhor local de venda | N5: Receita líquida / peça | O5: LUCRO / peça | P5: Margem | Q5: LUCRO TOTAL | R5: Custo do lote | S5: Barras líquidas (após retorno) | T5: Barras brutas | U5: Artefatos a comprar
E6: =IF(OR(A6="",B6="",C6=""),"",IFERROR(MATCH(A6&"|"&B6&"|"&C6,Itens!$A$4:$A$603,0),"?")) | F6: =IF(ISNUMBER($E6),INDEX(Itens!$G$4:$G$603,$E6),"") | G6: =IF(ISNUMBER($E6),INDEX(Itens!$Q$4:$Q$603,$E6),"") | H6: =IF(ISNUMBER($E6),INDEX(Itens!$R$4:$R$603,$E6),"") | I6: =IF(ISNUMBER($E6),INDEX(Itens!$S$4:$S$603,$E6),"") | J6: =IF(ISNUMBER($E6),INDEX(Itens!$U$4:$U$603,$E6),"") | K6: =IF(ISNUMBER($E6),INDEX(Itens!$V$4:$V$603,$E6),"") | L6: =IF(ISNUMBER($E6),INDEX(Itens!$O$4:$O$603,$E6),"") | M6: =IF(ISNUMBER($E6),INDEX(Itens!$P$4:$P$603,$E6),"") | N6: =IF(ISNUMBER($E6),INDEX(Itens!$W$4:$W$603,$E6),"") | O6: =IF(ISNUMBER($E6),INDEX(Itens!$X$4:$X$603,$E6),"") | P6: =IF(ISNUMBER($E6),INDEX(Itens!$Y$4:$Y$603,$E6),"") | Q6: =IF(AND(ISNUMBER(O6),ISNUMBER(D6)),O6*D6,0) | R6: =IF(AND(ISNUMBER(K6),ISNUMBER(D6)),K6*D6,0) | S6: =IF(AND(ISNUMBER(F6),ISNUMBER(D6)),D6*F6*(1-RetCraft),0) | T6: =IF(AND(ISNUMBER(F6),ISNUMBER(D6)),D6*F6,0) | U6: =IF(AND(ISNUMBER(H6),ISNUMBER(D6)),IF(H6>0,D6,0),0)
E7: =IF(OR(A7="",B7="",C7=""),"",IFERROR(MATCH(A7&"|"&B7&"|"&C7,Itens!$A$4:$A$603,0),"?")) | F7: =IF(ISNUMBER($E7),INDEX(Itens!$G$4:$G$603,$E7),"") | G7: =IF(ISNUMBER($E7),INDEX(Itens!$Q$4:$Q$603,$E7),"") | H7: =IF(ISNUMBER($E7),INDEX(Itens!$R$4:$R$603,$E7),"") | I7: =IF(ISNUMBER($E7),INDEX(Itens!$S$4:$S$603,$E7),"") | J7: =IF(ISNUMBER($E7),INDEX(Itens!$U$4:$U$603,$E7),"") | K7: =IF(ISNUMBER($E7),INDEX(Itens!$V$4:$V$603,$E7),"") | L7: =IF(ISNUMBER($E7),INDEX(Itens!$O$4:$O$603,$E7),"") | M7: =IF(ISNUMBER($E7),INDEX(Itens!$P$4:$P$603,$E7),"") | N7: =IF(ISNUMBER($E7),INDEX(Itens!$W$4:$W$603,$E7),"") | O7: =IF(ISNUMBER($E7),INDEX(Itens!$X$4:$X$603,$E7),"") | P7: =IF(ISNUMBER($E7),INDEX(Itens!$Y$4:$Y$603,$E7),"") | Q7: =IF(AND(ISNUMBER(O7),ISNUMBER(D7)),O7*D7,0) | R7: =IF(AND(ISNUMBER(K7),ISNUMBER(D7)),K7*D7,0) | S7: =IF(AND(ISNUMBER(F7),ISNUMBER(D7)),D7*F7*(1-RetCraft),0) | T7: =IF(AND(ISNUMBER(F7),ISNUMBER(D7)),D7*F7,0) | U7: =IF(AND(ISNUMBER(H7),ISNUMBER(D7)),IF(H7>0,D7,0),0)
E8: =IF(OR(A8="",B8="",C8=""),"",IFERROR(MATCH(A8&"|"&B8&"|"&C8,Itens!$A$4:$A$603,0),"?")) | F8: =IF(ISNUMBER($E8),INDEX(Itens!$G$4:$G$603,$E8),"") | G8: =IF(ISNUMBER($E8),INDEX(Itens!$Q$4:$Q$603,$E8),"") | H8: =IF(ISNUMBER($E8),INDEX(Itens!$R$4:$R$603,$E8),"") | I8: =IF(ISNUMBER($E8),INDEX(Itens!$S$4:$S$603,$E8),"") | J8: =IF(ISNUMBER($E8),INDEX(Itens!$U$4:$U$603,$E8),"") | K8: =IF(ISNUMBER($E8),INDEX(Itens!$V$4:$V$603,$E8),"") | L8: =IF(ISNUMBER($E8),INDEX(Itens!$O$4:$O$603,$E8),"") | M8: =IF(ISNUMBER($E8),INDEX(Itens!$P$4:$P$603,$E8),"") | N8: =IF(ISNUMBER($E8),INDEX(Itens!$W$4:$W$603,$E8),"") | O8: =IF(ISNUMBER($E8),INDEX(Itens!$X$4:$X$603,$E8),"") | P8: =IF(ISNUMBER($E8),INDEX(Itens!$Y$4:$Y$603,$E8),"") | Q8: =IF(AND(ISNUMBER(O8),ISNUMBER(D8)),O8*D8,0) | R8: =IF(AND(ISNUMBER(K8),ISNUMBER(D8)),K8*D8,0) | S8: =IF(AND(ISNUMBER(F8),ISNUMBER(D8)),D8*F8*(1-RetCraft),0) | T8: =IF(AND(ISNUMBER(F8),ISNUMBER(D8)),D8*F8,0) | U8: =IF(AND(ISNUMBER(H8),ISNUMBER(D8)),IF(H8>0,D8,0),0)
E9: =IF(OR(A9="",B9="",C9=""),"",IFERROR(MATCH(A9&"|"&B9&"|"&C9,Itens!$A$4:$A$603,0),"?")) | F9: =IF(ISNUMBER($E9),INDEX(Itens!$G$4:$G$603,$E9),"") | G9: =IF(ISNUMBER($E9),INDEX(Itens!$Q$4:$Q$603,$E9),"") | H9: =IF(ISNUMBER($E9),INDEX(Itens!$R$4:$R$603,$E9),"") | I9: =IF(ISNUMBER($E9),INDEX(Itens!$S$4:$S$603,$E9),"") | J9: =IF(ISNUMBER($E9),INDEX(Itens!$U$4:$U$603,$E9),"") | K9: =IF(ISNUMBER($E9),INDEX(Itens!$V$4:$V$603,$E9),"") | L9: =IF(ISNUMBER($E9),INDEX(Itens!$O$4:$O$603,$E9),"") | M9: =IF(ISNUMBER($E9),INDEX(Itens!$P$4:$P$603,$E9),"") | N9: =IF(ISNUMBER($E9),INDEX(Itens!$W$4:$W$603,$E9),"") | O9: =IF(ISNUMBER($E9),INDEX(Itens!$X$4:$X$603,$E9),"") | P9: =IF(ISNUMBER($E9),INDEX(Itens!$Y$4:$Y$603,$E9),"") | Q9: =IF(AND(ISNUMBER(O9),ISNUMBER(D9)),O9*D9,0) | R9: =IF(AND(ISNUMBER(K9),ISNUMBER(D9)),K9*D9,0) | S9: =IF(AND(ISNUMBER(F9),ISNUMBER(D9)),D9*F9*(1-RetCraft),0) | T9: =IF(AND(ISNUMBER(F9),ISNUMBER(D9)),D9*F9,0) | U9: =IF(AND(ISNUMBER(H9),ISNUMBER(D9)),IF(H9>0,D9,0),0)
E10: =IF(OR(A10="",B10="",C10=""),"",IFERROR(MATCH(A10&"|"&B10&"|"&C10,Itens!$A$4:$A$603,0),"?")) | F10: =IF(ISNUMBER($E10),INDEX(Itens!$G$4:$G$603,$E10),"") | G10: =IF(ISNUMBER($E10),INDEX(Itens!$Q$4:$Q$603,$E10),"") | H10: =IF(ISNUMBER($E10),INDEX(Itens!$R$4:$R$603,$E10),"") | I10: =IF(ISNUMBER($E10),INDEX(Itens!$S$4:$S$603,$E10),"") | J10: =IF(ISNUMBER($E10),INDEX(Itens!$U$4:$U$603,$E10),"") | K10: =IF(ISNUMBER($E10),INDEX(Itens!$V$4:$V$603,$E10),"") | L10: =IF(ISNUMBER($E10),INDEX(Itens!$O$4:$O$603,$E10),"") | M10: =IF(ISNUMBER($E10),INDEX(Itens!$P$4:$P$603,$E10),"") | N10: =IF(ISNUMBER($E10),INDEX(Itens!$W$4:$W$603,$E10),"") | O10: =IF(ISNUMBER($E10),INDEX(Itens!$X$4:$X$603,$E10),"") | P10: =IF(ISNUMBER($E10),INDEX(Itens!$Y$4:$Y$603,$E10),"") | Q10: =IF(AND(ISNUMBER(O10),ISNUMBER(D10)),O10*D10,0) | R10: =IF(AND(ISNUMBER(K10),ISNUMBER(D10)),K10*D10,0) | S10: =IF(AND(ISNUMBER(F10),ISNUMBER(D10)),D10*F10*(1-RetCraft),0) | T10: =IF(AND(ISNUMBER(F10),ISNUMBER(D10)),D10*F10,0) | U10: =IF(AND(ISNUMBER(H10),ISNUMBER(D10)),IF(H10>0,D10,0),0)
E11: =IF(OR(A11="",B11="",C11=""),"",IFERROR(MATCH(A11&"|"&B11&"|"&C11,Itens!$A$4:$A$603,0),"?")) | F11: =IF(ISNUMBER($E11),INDEX(Itens!$G$4:$G$603,$E11),"") | G11: =IF(ISNUMBER($E11),INDEX(Itens!$Q$4:$Q$603,$E11),"") | H11: =IF(ISNUMBER($E11),INDEX(Itens!$R$4:$R$603,$E11),"") | I11: =IF(ISNUMBER($E11),INDEX(Itens!$S$4:$S$603,$E11),"") | J11: =IF(ISNUMBER($E11),INDEX(Itens!$U$4:$U$603,$E11),"") | K11: =IF(ISNUMBER($E11),INDEX(Itens!$V$4:$V$603,$E11),"") | L11: =IF(ISNUMBER($E11),INDEX(Itens!$O$4:$O$603,$E11),"") | M11: =IF(ISNUMBER($E11),INDEX(Itens!$P$4:$P$603,$E11),"") | N11: =IF(ISNUMBER($E11),INDEX(Itens!$W$4:$W$603,$E11),"") | O11: =IF(ISNUMBER($E11),INDEX(Itens!$X$4:$X$603,$E11),"") | P11: =IF(ISNUMBER($E11),INDEX(Itens!$Y$4:$Y$603,$E11),"") | Q11: =IF(AND(ISNUMBER(O11),ISNUMBER(D11)),O11*D11,0) | R11: =IF(AND(ISNUMBER(K11),ISNUMBER(D11)),K11*D11,0) | S11: =IF(AND(ISNUMBER(F11),ISNUMBER(D11)),D11*F11*(1-RetCraft),0) | T11: =IF(AND(ISNUMBER(F11),ISNUMBER(D11)),D11*F11,0) | U11: =IF(AND(ISNUMBER(H11),ISNUMBER(D11)),IF(H11>0,D11,0),0)
E12: =IF(OR(A12="",B12="",C12=""),"",IFERROR(MATCH(A12&"|"&B12&"|"&C12,Itens!$A$4:$A$603,0),"?")) | F12: =IF(ISNUMBER($E12),INDEX(Itens!$G$4:$G$603,$E12),"") | G12: =IF(ISNUMBER($E12),INDEX(Itens!$Q$4:$Q$603,$E12),"") | H12: =IF(ISNUMBER($E12),INDEX(Itens!$R$4:$R$603,$E12),"") | I12: =IF(ISNUMBER($E12),INDEX(Itens!$S$4:$S$603,$E12),"") | J12: =IF(ISNUMBER($E12),INDEX(Itens!$U$4:$U$603,$E12),"") | K12: =IF(ISNUMBER($E12),INDEX(Itens!$V$4:$V$603,$E12),"") | L12: =IF(ISNUMBER($E12),INDEX(Itens!$O$4:$O$603,$E12),"") | M12: =IF(ISNUMBER($E12),INDEX(Itens!$P$4:$P$603,$E12),"") | N12: =IF(ISNUMBER($E12),INDEX(Itens!$W$4:$W$603,$E12),"") | O12: =IF(ISNUMBER($E12),INDEX(Itens!$X$4:$X$603,$E12),"") | P12: =IF(ISNUMBER($E12),INDEX(Itens!$Y$4:$Y$603,$E12),"") | Q12: =IF(AND(ISNUMBER(O12),ISNUMBER(D12)),O12*D12,0) | R12: =IF(AND(ISNUMBER(K12),ISNUMBER(D12)),K12*D12,0) | S12: =IF(AND(ISNUMBER(F12),ISNUMBER(D12)),D12*F12*(1-RetCraft),0) | T12: =IF(AND(ISNUMBER(F12),ISNUMBER(D12)),D12*F12,0) | U12: =IF(AND(ISNUMBER(H12),ISNUMBER(D12)),IF(H12>0,D12,0),0)
E13: =IF(OR(A13="",B13="",C13=""),"",IFERROR(MATCH(A13&"|"&B13&"|"&C13,Itens!$A$4:$A$603,0),"?")) | F13: =IF(ISNUMBER($E13),INDEX(Itens!$G$4:$G$603,$E13),"") | G13: =IF(ISNUMBER($E13),INDEX(Itens!$Q$4:$Q$603,$E13),"") | H13: =IF(ISNUMBER($E13),INDEX(Itens!$R$4:$R$603,$E13),"") | I13: =IF(ISNUMBER($E13),INDEX(Itens!$S$4:$S$603,$E13),"") | J13: =IF(ISNUMBER($E13),INDEX(Itens!$U$4:$U$603,$E13),"") | K13: =IF(ISNUMBER($E13),INDEX(Itens!$V$4:$V$603,$E13),"") | L13: =IF(ISNUMBER($E13),INDEX(Itens!$O$4:$O$603,$E13),"") | M13: =IF(ISNUMBER($E13),INDEX(Itens!$P$4:$P$603,$E13),"") | N13: =IF(ISNUMBER($E13),INDEX(Itens!$W$4:$W$603,$E13),"") | O13: =IF(ISNUMBER($E13),INDEX(Itens!$X$4:$X$603,$E13),"") | P13: =IF(ISNUMBER($E13),INDEX(Itens!$Y$4:$Y$603,$E13),"") | Q13: =IF(AND(ISNUMBER(O13),ISNUMBER(D13)),O13*D13,0) | R13: =IF(AND(ISNUMBER(K13),ISNUMBER(D13)),K13*D13,0) | S13: =IF(AND(ISNUMBER(F13),ISNUMBER(D13)),D13*F13*(1-RetCraft),0) | T13: =IF(AND(ISNUMBER(F13),ISNUMBER(D13)),D13*F13,0) | U13: =IF(AND(ISNUMBER(H13),ISNUMBER(D13)),IF(H13>0,D13,0),0)
E14: =IF(OR(A14="",B14="",C14=""),"",IFERROR(MATCH(A14&"|"&B14&"|"&C14,Itens!$A$4:$A$603,0),"?")) | F14: =IF(ISNUMBER($E14),INDEX(Itens!$G$4:$G$603,$E14),"") | G14: =IF(ISNUMBER($E14),INDEX(Itens!$Q$4:$Q$603,$E14),"") | H14: =IF(ISNUMBER($E14),INDEX(Itens!$R$4:$R$603,$E14),"") | I14: =IF(ISNUMBER($E14),INDEX(Itens!$S$4:$S$603,$E14),"") | J14: =IF(ISNUMBER($E14),INDEX(Itens!$U$4:$U$603,$E14),"") | K14: =IF(ISNUMBER($E14),INDEX(Itens!$V$4:$V$603,$E14),"") | L14: =IF(ISNUMBER($E14),INDEX(Itens!$O$4:$O$603,$E14),"") | M14: =IF(ISNUMBER($E14),INDEX(Itens!$P$4:$P$603,$E14),"") | N14: =IF(ISNUMBER($E14),INDEX(Itens!$W$4:$W$603,$E14),"") | O14: =IF(ISNUMBER($E14),INDEX(Itens!$X$4:$X$603,$E14),"") | P14: =IF(ISNUMBER($E14),INDEX(Itens!$Y$4:$Y$603,$E14),"") | Q14: =IF(AND(ISNUMBER(O14),ISNUMBER(D14)),O14*D14,0) | R14: =IF(AND(ISNUMBER(K14),ISNUMBER(D14)),K14*D14,0) | S14: =IF(AND(ISNUMBER(F14),ISNUMBER(D14)),D14*F14*(1-RetCraft),0) | T14: =IF(AND(ISNUMBER(F14),ISNUMBER(D14)),D14*F14,0) | U14: =IF(AND(ISNUMBER(H14),ISNUMBER(D14)),IF(H14>0,D14,0),0)
E15: =IF(OR(A15="",B15="",C15=""),"",IFERROR(MATCH(A15&"|"&B15&"|"&C15,Itens!$A$4:$A$603,0),"?")) | F15: =IF(ISNUMBER($E15),INDEX(Itens!$G$4:$G$603,$E15),"") | G15: =IF(ISNUMBER($E15),INDEX(Itens!$Q$4:$Q$603,$E15),"") | H15: =IF(ISNUMBER($E15),INDEX(Itens!$R$4:$R$603,$E15),"") | I15: =IF(ISNUMBER($E15),INDEX(Itens!$S$4:$S$603,$E15),"") | J15: =IF(ISNUMBER($E15),INDEX(Itens!$U$4:$U$603,$E15),"") | K15: =IF(ISNUMBER($E15),INDEX(Itens!$V$4:$V$603,$E15),"") | L15: =IF(ISNUMBER($E15),INDEX(Itens!$O$4:$O$603,$E15),"") | M15: =IF(ISNUMBER($E15),INDEX(Itens!$P$4:$P$603,$E15),"") | N15: =IF(ISNUMBER($E15),INDEX(Itens!$W$4:$W$603,$E15),"") | O15: =IF(ISNUMBER($E15),INDEX(Itens!$X$4:$X$603,$E15),"") | P15: =IF(ISNUMBER($E15),INDEX(Itens!$Y$4:$Y$603,$E15),"") | Q15: =IF(AND(ISNUMBER(O15),ISNUMBER(D15)),O15*D15,0) | R15: =IF(AND(ISNUMBER(K15),ISNUMBER(D15)),K15*D15,0) | S15: =IF(AND(ISNUMBER(F15),ISNUMBER(D15)),D15*F15*(1-RetCraft),0) | T15: =IF(AND(ISNUMBER(F15),ISNUMBER(D15)),D15*F15,0) | U15: =IF(AND(ISNUMBER(H15),ISNUMBER(D15)),IF(H15>0,D15,0),0)
E16: =IF(OR(A16="",B16="",C16=""),"",IFERROR(MATCH(A16&"|"&B16&"|"&C16,Itens!$A$4:$A$603,0),"?")) | F16: =IF(ISNUMBER($E16),INDEX(Itens!$G$4:$G$603,$E16),"") | G16: =IF(ISNUMBER($E16),INDEX(Itens!$Q$4:$Q$603,$E16),"") | H16: =IF(ISNUMBER($E16),INDEX(Itens!$R$4:$R$603,$E16),"") | I16: =IF(ISNUMBER($E16),INDEX(Itens!$S$4:$S$603,$E16),"") | J16: =IF(ISNUMBER($E16),INDEX(Itens!$U$4:$U$603,$E16),"") | K16: =IF(ISNUMBER($E16),INDEX(Itens!$V$4:$V$603,$E16),"") | L16: =IF(ISNUMBER($E16),INDEX(Itens!$O$4:$O$603,$E16),"") | M16: =IF(ISNUMBER($E16),INDEX(Itens!$P$4:$P$603,$E16),"") | N16: =IF(ISNUMBER($E16),INDEX(Itens!$W$4:$W$603,$E16),"") | O16: =IF(ISNUMBER($E16),INDEX(Itens!$X$4:$X$603,$E16),"") | P16: =IF(ISNUMBER($E16),INDEX(Itens!$Y$4:$Y$603,$E16),"") | Q16: =IF(AND(ISNUMBER(O16),ISNUMBER(D16)),O16*D16,0) | R16: =IF(AND(ISNUMBER(K16),ISNUMBER(D16)),K16*D16,0) | S16: =IF(AND(ISNUMBER(F16),ISNUMBER(D16)),D16*F16*(1-RetCraft),0) | T16: =IF(AND(ISNUMBER(F16),ISNUMBER(D16)),D16*F16,0) | U16: =IF(AND(ISNUMBER(H16),ISNUMBER(D16)),IF(H16>0,D16,0),0)
E17: =IF(OR(A17="",B17="",C17=""),"",IFERROR(MATCH(A17&"|"&B17&"|"&C17,Itens!$A$4:$A$603,0),"?")) | F17: =IF(ISNUMBER($E17),INDEX(Itens!$G$4:$G$603,$E17),"") | G17: =IF(ISNUMBER($E17),INDEX(Itens!$Q$4:$Q$603,$E17),"") | H17: =IF(ISNUMBER($E17),INDEX(Itens!$R$4:$R$603,$E17),"") | I17: =IF(ISNUMBER($E17),INDEX(Itens!$S$4:$S$603,$E17),"") | J17: =IF(ISNUMBER($E17),INDEX(Itens!$U$4:$U$603,$E17),"") | K17: =IF(ISNUMBER($E17),INDEX(Itens!$V$4:$V$603,$E17),"") | L17: =IF(ISNUMBER($E17),INDEX(Itens!$O$4:$O$603,$E17),"") | M17: =IF(ISNUMBER($E17),INDEX(Itens!$P$4:$P$603,$E17),"") | N17: =IF(ISNUMBER($E17),INDEX(Itens!$W$4:$W$603,$E17),"") | O17: =IF(ISNUMBER($E17),INDEX(Itens!$X$4:$X$603,$E17),"") | P17: =IF(ISNUMBER($E17),INDEX(Itens!$Y$4:$Y$603,$E17),"") | Q17: =IF(AND(ISNUMBER(O17),ISNUMBER(D17)),O17*D17,0) | R17: =IF(AND(ISNUMBER(K17),ISNUMBER(D17)),K17*D17,0) | S17: =IF(AND(ISNUMBER(F17),ISNUMBER(D17)),D17*F17*(1-RetCraft),0) | T17: =IF(AND(ISNUMBER(F17),ISNUMBER(D17)),D17*F17,0) | U17: =IF(AND(ISNUMBER(H17),ISNUMBER(D17)),IF(H17>0,D17,0),0)
... E35: =IF(OR(A35="",B35="",C35=""),"",IFERROR(MATCH(A35&"|"&B35&"|"&C35,Itens!$A$4:$A$603,0),"?")) | F35: =IF(ISNUMBER($E35),INDEX(Itens!$G$4:$G$603,$E35),"") | G35: =IF(ISNUMBER($E35),INDEX(Itens!$Q$4:$Q$603,$E35),"") | H35: =IF(ISNUMBER($E35),INDEX(Itens!$R$4:$R$603,$E35),"") | I35: =IF(ISNUMBER($E35),INDEX(Itens!$S$4:$S$603,$E35),"") | J35: =IF(ISNUMBER($E35),INDEX(Itens!$U$4:$U$603,$E35),"") | K35: =IF(ISNUMBER($E35),INDEX(Itens!$V$4:$V$603,$E35),"") | L35: =IF(ISNUMBER($E35),INDEX(Itens!$O$4:$O$603,$E35),"") | M35: =IF(ISNUMBER($E35),INDEX(Itens!$P$4:$P$603,$E35),"") | N35: =IF(ISNUMBER($E35),INDEX(Itens!$W$4:$W$603,$E35),"") | O35: =IF(ISNUMBER($E35),INDEX(Itens!$X$4:$X$603,$E35),"") | P35: =IF(ISNUMBER($E35),INDEX(Itens!$Y$4:$Y$603,$E35),"") | Q35: =IF(AND(ISNUMBER(O35),ISNUMBER(D35)),O35*D35,0) | R35: =IF(AND(ISNUMBER(K35),ISNUMBER(D35)),K35*D35,0) | S35: =IF(AND(ISNUMBER(F35),ISNUMBER(D35)),D35*F35*(1-RetCraft),0) | T35: =IF(AND(ISNUMBER(F35),ISNUMBER(D35)),D35*F35,0) | U35: =IF(AND(ISNUMBER(H35),ISNUMBER(D35)),IF(H35>0,D35,0),0)

Sheet Lista_Compras
A1: Lista de compras para o que está planejado na aba Craft
A2: Quantidades líquidas (descontado o retorno de recursos esperado). Linhas com zero ficam vazias.
A3: TOTAL A INVESTIR (barras + minério + artefatos): | F3: =E37+K37+Q37 | H3: Lucro esperado: | I3: =Craft!D3
A5: BARRAS a comprar | B5: Qtd | C5: Cidade | D5: Preço unit. | E5: Total | G5: MINÉRIO a comprar | H5: Qtd | I5: Cidade | J5: Preço unit. | K5: Total | M5: ARTEFATOS a comprar | N5: Qtd | O5: Cidade | P5: Preço unit. | Q5: Total
A6: T2.0 | B6: =Refino!Q3 | C6: =IF(B6>0,Refino!J3,"") | D6: =IF(B6>0,Refino!I3,"") | E6: =Refino!T3 | G6: T2.0 | H6: =Refino!S3 | I6: =IF(H6>0,Refino!V3,"") | J6: =IF(H6>0,Refino!G3,"") | K6: =Refino!U3 | M6: =IF(Craft!U6>0,Craft!A6&" "&Craft!B6&" "&Craft!C6,"") | N6: =Craft!U6 | O6: =IF(N6>0,Craft!I6,"") | P6: =IF(N6>0,Craft!H6,"") | Q6: =IF(AND(N6>0,ISNUMBER(P6)),N6*P6,0)
A7: T3.0 | B7: =Refino!Q4 | C7: =IF(B7>0,Refino!J4,"") | D7: =IF(B7>0,Refino!I4,"") | E7: =Refino!T4 | G7: T3.0 | H7: =Refino!S4 | I7: =IF(H7>0,Refino!V4,"") | J7: =IF(H7>0,Refino!G4,"") | K7: =Refino!U4 | M7: =IF(Craft!U7>0,Craft!A7&" "&Craft!B7&" "&Craft!C7,"") | N7: =Craft!U7 | O7: =IF(N7>0,Craft!I7,"") | P7: =IF(N7>0,Craft!H7,"") | Q7: =IF(AND(N7>0,ISNUMBER(P7)),N7*P7,0)
A8: T4.0 | B8: =Refino!Q5 | C8: =IF(B8>0,Refino!J5,"") | D8: =IF(B8>0,Refino!I5,"") | E8: =Refino!T5 | G8: T4.0 | H8: =Refino!S5 | I8: =IF(H8>0,Refino!V5,"") | J8: =IF(H8>0,Refino!G5,"") | K8: =Refino!U5 | M8: =IF(Craft!U8>0,Craft!A8&" "&Craft!B8&" "&Craft!C8,"") | N8: =Craft!U8 | O8: =IF(N8>0,Craft!I8,"") | P8: =IF(N8>0,Craft!H8,"") | Q8: =IF(AND(N8>0,ISNUMBER(P8)),N8*P8,0)
A9: T4.1 | B9: =Refino!Q6 | C9: =IF(B9>0,Refino!J6,"") | D9: =IF(B9>0,Refino!I6,"") | E9: =Refino!T6 | G9: T4.1 | H9: =Refino!S6 | I9: =IF(H9>0,Refino!V6,"") | J9: =IF(H9>0,Refino!G6,"") | K9: =Refino!U6 | M9: =IF(Craft!U9>0,Craft!A9&" "&Craft!B9&" "&Craft!C9,"") | N9: =Craft!U9 | O9: =IF(N9>0,Craft!I9,"") | P9: =IF(N9>0,Craft!H9,"") | Q9: =IF(AND(N9>0,ISNUMBER(P9)),N9*P9,0)
A10: T4.2 | B10: =Refino!Q7 | C10: =IF(B10>0,Refino!J7,"") | D10: =IF(B10>0,Refino!I7,"") | E10: =Refino!T7 | G10: T4.2 | H10: =Refino!S7 | I10: =IF(H10>0,Refino!V7,"") | J10: =IF(H10>0,Refino!G7,"") | K10: =Refino!U7 | M10: =IF(Craft!U10>0,Craft!A10&" "&Craft!B10&" "&Craft!C10,"") | N10: =Craft!U10 | O10: =IF(N10>0,Craft!I10,"") | P10: =IF(N10>0,Craft!H10,"") | Q10: =IF(AND(N10>0,ISNUMBER(P10)),N10*P10,0)
A11: T4.3 | B11: =Refino!Q8 | C11: =IF(B11>0,Refino!J8,"") | D11: =IF(B11>0,Refino!I8,"") | E11: =Refino!T8 | G11: T4.3 | H11: =Refino!S8 | I11: =IF(H11>0,Refino!V8,"") | J11: =IF(H11>0,Refino!G8,"") | K11: =Refino!U8 | M11: =IF(Craft!U11>0,Craft!A11&" "&Craft!B11&" "&Craft!C11,"") | N11: =Craft!U11 | O11: =IF(N11>0,Craft!I11,"") | P11: =IF(N11>0,Craft!H11,"") | Q11: =IF(AND(N11>0,ISNUMBER(P11)),N11*P11,0)
A12: T4.4 | B12: =Refino!Q9 | C12: =IF(B12>0,Refino!J9,"") | D12: =IF(B12>0,Refino!I9,"") | E12: =Refino!T9 | G12: T4.4 | H12: =Refino!S9 | I12: =IF(H12>0,Refino!V9,"") | J12: =IF(H12>0,Refino!G9,"") | K12: =Refino!U9 | M12: =IF(Craft!U12>0,Craft!A12&" "&Craft!B12&" "&Craft!C12,"") | N12: =Craft!U12 | O12: =IF(N12>0,Craft!I12,"") | P12: =IF(N12>0,Craft!H12,"") | Q12: =IF(AND(N12>0,ISNUMBER(P12)),N12*P12,0)
A13: T5.0 | B13: =Refino!Q10 | C13: =IF(B13>0,Refino!J10,"") | D13: =IF(B13>0,Refino!I10,"") | E13: =Refino!T10 | G13: T5.0 | H13: =Refino!S10 | I13: =IF(H13>0,Refino!V10,"") | J13: =IF(H13>0,Refino!G10,"") | K13: =Refino!U10 | M13: =IF(Craft!U13>0,Craft!A13&" "&Craft!B13&" "&Craft!C13,"") | N13: =Craft!U13 | O13: =IF(N13>0,Craft!I13,"") | P13: =IF(N13>0,Craft!H13,"") | Q13: =IF(AND(N13>0,ISNUMBER(P13)),N13*P13,0)
A14: T5.1 | B14: =Refino!Q11 | C14: =IF(B14>0,Refino!J11,"") | D14: =IF(B14>0,Refino!I11,"") | E14: =Refino!T11 | G14: T5.1 | H14: =Refino!S11 | I14: =IF(H14>0,Refino!V11,"") | J14: =IF(H14>0,Refino!G11,"") | K14: =Refino!U11 | M14: =IF(Craft!U14>0,Craft!A14&" "&Craft!B14&" "&Craft!C14,"") | N14: =Craft!U14 | O14: =IF(N14>0,Craft!I14,"") | P14: =IF(N14>0,Craft!H14,"") | Q14: =IF(AND(N14>0,ISNUMBER(P14)),N14*P14,0)
A15: T5.2 | B15: =Refino!Q12 | C15: =IF(B15>0,Refino!J12,"") | D15: =IF(B15>0,Refino!I12,"") | E15: =Refino!T12 | G15: T5.2 | H15: =Refino!S12 | I15: =IF(H15>0,Refino!V12,"") | J15: =IF(H15>0,Refino!G12,"") | K15: =Refino!U12 | M15: =IF(Craft!U15>0,Craft!A15&" "&Craft!B15&" "&Craft!C15,"") | N15: =Craft!U15 | O15: =IF(N15>0,Craft!I15,"") | P15: =IF(N15>0,Craft!H15,"") | Q15: =IF(AND(N15>0,ISNUMBER(P15)),N15*P15,0)
A16: T5.3 | B16: =Refino!Q13 | C16: =IF(B16>0,Refino!J13,"") | D16: =IF(B16>0,Refino!I13,"") | E16: =Refino!T13 | G16: T5.3 | H16: =Refino!S13 | I16: =IF(H16>0,Refino!V13,"") | J16: =IF(H16>0,Refino!G13,"") | K16: =Refino!U13 | M16: =IF(Craft!U16>0,Craft!A16&" "&Craft!B16&" "&Craft!C16,"") | N16: =Craft!U16 | O16: =IF(N16>0,Craft!I16,"") | P16: =IF(N16>0,Craft!H16,"") | Q16: =IF(AND(N16>0,ISNUMBER(P16)),N16*P16,0)
A17: T5.4 | B17: =Refino!Q14 | C17: =IF(B17>0,Refino!J14,"") | D17: =IF(B17>0,Refino!I14,"") | E17: =Refino!T14 | G17: T5.4 | H17: =Refino!S14 | I17: =IF(H17>0,Refino!V14,"") | J17: =IF(H17>0,Refino!G14,"") | K17: =Refino!U14 | M17: =IF(Craft!U17>0,Craft!A17&" "&Craft!B17&" "&Craft!C17,"") | N17: =Craft!U17 | O17: =IF(N17>0,Craft!I17,"") | P17: =IF(N17>0,Craft!H17,"") | Q17: =IF(AND(N17>0,ISNUMBER(P17)),N17*P17,0)
... A32: T8.4 | B32: =Refino!Q29 | C32: =IF(B32>0,Refino!J29,"") | D32: =IF(B32>0,Refino!I29,"") | E32: =Refino!T29 | G32: T8.4 | H32: =Refino!S29 | I32: =IF(H32>0,Refino!V29,"") | J32: =IF(H32>0,Refino!G29,"") | K32: =Refino!U29 | M32: =IF(Craft!U32>0,Craft!A32&" "&Craft!B32&" "&Craft!C32,"") | N32: =Craft!U32 | O32: =IF(N32>0,Craft!I32,"") | P32: =IF(N32>0,Craft!H32,"") | Q32: =IF(AND(N32>0,ISNUMBER(P32)),N32*P32,0)
M33: =IF(Craft!U33>0,Craft!A33&" "&Craft!B33&" "&Craft!C33,"") | N33: =Craft!U33 | O33: =IF(N33>0,Craft!I33,"") | P33: =IF(N33>0,Craft!H33,"") | Q33: =IF(AND(N33>0,ISNUMBER(P33)),N33*P33,0)
M34: =IF(Craft!U34>0,Craft!A34&" "&Craft!B34&" "&Craft!C34,"") | N34: =Craft!U34 | O34: =IF(N34>0,Craft!I34,"") | P34: =IF(N34>0,Craft!H34,"") | Q34: =IF(AND(N34>0,ISNUMBER(P34)),N34*P34,0)
M35: =IF(Craft!U35>0,Craft!A35&" "&Craft!B35&" "&Craft!C35,"") | N35: =Craft!U35 | O35: =IF(N35>0,Craft!I35,"") | P35: =IF(N35>0,Craft!H35,"") | Q35: =IF(AND(N35>0,ISNUMBER(P35)),N35*P35,0)
A37: Subtotal barras | E37: =SUM(E6:E35) | G37: Subtotal minério | K37: =SUM(K6:K35) | M37: Subtotal artefatos | Q37: =SUM(Q6:Q35)

Sheet Itens
A1: Preços de venda e lucro de todas as peças de placa
A2: Preencha o preço de venda por cidade, Caerleon e Mercado Negro. Use o filtro (setas do cabeçalho) para ordenar por lucro/margem.
A3: Chave | B3: Variante | C3: Peça | D3: Tier | E3: Tier nº | F3: Encant. | G3: Qtd barras | H3: Thetford | I3: Martlock | J3: Bridgewatch | K3: Lymhurst | L3: Fort Sterling | M3: Caerleon | N3: Mercado Negro | O3: Melhor preço de venda | P3: Melhor local | Q3: Custo barras (líq. retorno) | R3: Artefato | S3: Cidade do artefato | T3: Valor do item (IV) | U3: Taxa do ferreiro | V3: CUSTO TOTAL | W3: Receita líquida (após taxa) | X3: LUCRO por item | Y3: Margem
A4: Soldado (Soldier)|Armadura|T4.0 | B4: Soldado (Soldier) | C4: Armadura | D4: T4.0 | E4: 4 | F4: 0 | G4: 16 | O4: =IF(COUNT(H4:N4)=0,"",MAX(H4:N4)) | P4: =IF(O4="","",INDEX($H$3:$N$3,MATCH(O4,H4:N4,0))) | Q4: =IF(Refino!$L$5="","",G4*Refino!$L$5*(1-RetCraft)) | R4: 0 | S4: - | T4: =G4*Refino!$D$5 | U4: =T4*0.1125*FeeCraft/100 | V4: =IF(OR(Q4="",R4=""),"",Q4+R4+U4) | W4: =IF(O4="","",O4*(1-TaxaVenda)) | X4: =IF(OR(V4="",W4=""),"",W4-V4) | Y4: =IF(X4="","",X4/V4)
A5: Soldado (Soldier)|Armadura|T4.1 | B5: Soldado (Soldier) | C5: Armadura | D5: T4.1 | E5: 4 | F5: 1 | G5: 16 | O5: =IF(COUNT(H5:N5)=0,"",MAX(H5:N5)) | P5: =IF(O5="","",INDEX($H$3:$N$3,MATCH(O5,H5:N5,0))) | Q5: =IF(Refino!$L$6="","",G5*Refino!$L$6*(1-RetCraft)) | R5: 0 | S5: - | T5: =G5*Refino!$D$6 | U5: =T5*0.1125*FeeCraft/100 | V5: =IF(OR(Q5="",R5=""),"",Q5+R5+U5) | W5: =IF(O5="","",O5*(1-TaxaVenda)) | X5: =IF(OR(V5="",W5=""),"",W5-V5) | Y5: =IF(X5="","",X5/V5)
A6: Soldado (Soldier)|Armadura|T4.2 | B6: Soldado (Soldier) | C6: Armadura | D6: T4.2 | E6: 4 | F6: 2 | G6: 16 | O6: =IF(COUNT(H6:N6)=0,"",MAX(H6:N6)) | P6: =IF(O6="","",INDEX($H$3:$N$3,MATCH(O6,H6:N6,0))) | Q6: =IF(Refino!$L$7="","",G6*Refino!$L$7*(1-RetCraft)) | R6: 0 | S6: - | T6: =G6*Refino!$D$7 | U6: =T6*0.1125*FeeCraft/100 | V6: =IF(OR(Q6="",R6=""),"",Q6+R6+U6) | W6: =IF(O6="","",O6*(1-TaxaVenda)) | X6: =IF(OR(V6="",W6=""),"",W6-V6) | Y6: =IF(X6="","",X6/V6)
A7: Soldado (Soldier)|Armadura|T4.3 | B7: Soldado (Soldier) | C7: Armadura | D7: T4.3 | E7: 4 | F7: 3 | G7: 16 | O7: =IF(COUNT(H7:N7)=0,"",MAX(H7:N7)) | P7: =IF(O7="","",INDEX($H$3:$N$3,MATCH(O7,H7:N7,0))) | Q7: =IF(Refino!$L$8="","",G7*Refino!$L$8*(1-RetCraft)) | R7: 0 | S7: - | T7: =G7*Refino!$D$8 | U7: =T7*0.1125*FeeCraft/100 | V7: =IF(OR(Q7="",R7=""),"",Q7+R7+U7) | W7: =IF(O7="","",O7*(1-TaxaVenda)) | X7: =IF(OR(V7="",W7=""),"",W7-V7) | Y7: =IF(X7="","",X7/V7)
A8: Soldado (Soldier)|Armadura|T4.4 | B8: Soldado (Soldier) | C8: Armadura | D8: T4.4 | E8: 4 | F8: 4 | G8: 16 | O8: =IF(COUNT(H8:N8)=0,"",MAX(H8:N8)) | P8: =IF(O8="","",INDEX($H$3:$N$3,MATCH(O8,H8:N8,0))) | Q8: =IF(Refino!$L$9="","",G8*Refino!$L$9*(1-RetCraft)) | R8: 0 | S8: - | T8: =G8*Refino!$D$9 | U8: =T8*0.1125*FeeCraft/100 | V8: =IF(OR(Q8="",R8=""),"",Q8+R8+U8) | W8: =IF(O8="","",O8*(1-TaxaVenda)) | X8: =IF(OR(V8="",W8=""),"",W8-V8) | Y8: =IF(X8="","",X8/V8)
A9: Soldado (Soldier)|Armadura|T5.0 | B9: Soldado (Soldier) | C9: Armadura | D9: T5.0 | E9: 5 | F9: 0 | G9: 16 | O9: =IF(COUNT(H9:N9)=0,"",MAX(H9:N9)) | P9: =IF(O9="","",INDEX($H$3:$N$3,MATCH(O9,H9:N9,0))) | Q9: =IF(Refino!$L$10="","",G9*Refino!$L$10*(1-RetCraft)) | R9: 0 | S9: - | T9: =G9*Refino!$D$10 | U9: =T9*0.1125*FeeCraft/100 | V9: =IF(OR(Q9="",R9=""),"",Q9+R9+U9) | W9: =IF(O9="","",O9*(1-TaxaVenda)) | X9: =IF(OR(V9="",W9=""),"",W9-V9) | Y9: =IF(X9="","",X9/V9)
A10: Soldado (Soldier)|Armadura|T5.1 | B10: Soldado (Soldier) | C10: Armadura | D10: T5.1 | E10: 5 | F10: 1 | G10: 16 | O10: =IF(COUNT(H10:N10)=0,"",MAX(H10:N10)) | P10: =IF(O10="","",INDEX($H$3:$N$3,MATCH(O10,H10:N10,0))) | Q10: =IF(Refino!$L$11="","",G10*Refino!$L$11*(1-RetCraft)) | R10: 0 | S10: - | T10: =G10*Refino!$D$11 | U10: =T10*0.1125*FeeCraft/100 | V10: =IF(OR(Q10="",R10=""),"",Q10+R10+U10) | W10: =IF(O10="","",O10*(1-TaxaVenda)) | X10: =IF(OR(V10="",W10=""),"",W10-V10) | Y10: =IF(X10="","",X10/V10)
A11: Soldado (Soldier)|Armadura|T5.2 | B11: Soldado (Soldier) | C11: Armadura | D11: T5.2 | E11: 5 | F11: 2 | G11: 16 | O11: =IF(COUNT(H11:N11)=0,"",MAX(H11:N11)) | P11: =IF(O11="","",INDEX($H$3:$N$3,MATCH(O11,H11:N11,0))) | Q11: =IF(Refino!$L$12="","",G11*Refino!$L$12*(1-RetCraft)) | R11: 0 | S11: - | T11: =G11*Refino!$D$12 | U11: =T11*0.1125*FeeCraft/100 | V11: =IF(OR(Q11="",R11=""),"",Q11+R11+U11) | W11: =IF(O11="","",O11*(1-TaxaVenda)) | X11: =IF(OR(V11="",W11=""),"",W11-V11) | Y11: =IF(X11="","",X11/V11)
A12: Soldado (Soldier)|Armadura|T5.3 | B12: Soldado (Soldier) | C12: Armadura | D12: T5.3 | E12: 5 | F12: 3 | G12: 16 | O12: =IF(COUNT(H12:N12)=0,"",MAX(H12:N12)) | P12: =IF(O12="","",INDEX($H$3:$N$3,MATCH(O12,H12:N12,0))) | Q12: =IF(Refino!$L$13="","",G12*Refino!$L$13*(1-RetCraft)) | R12: 0 | S12: - | T12: =G12*Refino!$D$13 | U12: =T12*0.1125*FeeCraft/100 | V12: =IF(OR(Q12="",R12=""),"",Q12+R12+U12) | W12: =IF(O12="","",O12*(1-TaxaVenda)) | X12: =IF(OR(V12="",W12=""),"",W12-V12) | Y12: =IF(X12="","",X12/V12)
A13: Soldado (Soldier)|Armadura|T5.4 | B13: Soldado (Soldier) | C13: Armadura | D13: T5.4 | E13: 5 | F13: 4 | G13: 16 | O13: =IF(COUNT(H13:N13)=0,"",MAX(H13:N13)) | P13: =IF(O13="","",INDEX($H$3:$N$3,MATCH(O13,H13:N13,0))) | Q13: =IF(Refino!$L$14="","",G13*Refino!$L$14*(1-RetCraft)) | R13: 0 | S13: - | T13: =G13*Refino!$D$14 | U13: =T13*0.1125*FeeCraft/100 | V13: =IF(OR(Q13="",R13=""),"",Q13+R13+U13) | W13: =IF(O13="","",O13*(1-TaxaVenda)) | X13: =IF(OR(V13="",W13=""),"",W13-V13) | Y13: =IF(X13="","",X13/V13)
A14: Soldado (Soldier)|Armadura|T6.0 | B14: Soldado (Soldier) | C14: Armadura | D14: T6.0 | E14: 6 | F14: 0 | G14: 16 | O14: =IF(COUNT(H14:N14)=0,"",MAX(H14:N14)) | P14: =IF(O14="","",INDEX($H$3:$N$3,MATCH(O14,H14:N14,0))) | Q14: =IF(Refino!$L$15="","",G14*Refino!$L$15*(1-RetCraft)) | R14: 0 | S14: - | T14: =G14*Refino!$D$15 | U14: =T14*0.1125*FeeCraft/100 | V14: =IF(OR(Q14="",R14=""),"",Q14+R14+U14) | W14: =IF(O14="","",O14*(1-TaxaVenda)) | X14: =IF(OR(V14="",W14=""),"",W14-V14) | Y14: =IF(X14="","",X14/V14)
A15: Soldado (Soldier)|Armadura|T6.1 | B15: Soldado (Soldier) | C15: Armadura | D15: T6.1 | E15: 6 | F15: 1 | G15: 16 | O15: =IF(COUNT(H15:N15)=0,"",MAX(H15:N15)) | P15: =IF(O15="","",INDEX($H$3:$N$3,MATCH(O15,H15:N15,0))) | Q15: =IF(Refino!$L$16="","",G15*Refino!$L$16*(1-RetCraft)) | R15: 0 | S15: - | T15: =G15*Refino!$D$16 | U15: =T15*0.1125*FeeCraft/100 | V15: =IF(OR(Q15="",R15=""),"",Q15+R15+U15) | W15: =IF(O15="","",O15*(1-TaxaVenda)) | X15: =IF(OR(V15="",W15=""),"",W15-V15) | Y15: =IF(X15="","",X15/V15)
A16: Soldado (Soldier)|Armadura|T6.2 | B16: Soldado (Soldier) | C16: Armadura | D16: T6.2 | E16: 6 | F16: 2 | G16: 16 | O16: =IF(COUNT(H16:N16)=0,"",MAX(H16:N16)) | P16: =IF(O16="","",INDEX($H$3:$N$3,MATCH(O16,H16:N16,0))) | Q16: =IF(Refino!$L$17="","",G16*Refino!$L$17*(1-RetCraft)) | R16: 0 | S16: - | T16: =G16*Refino!$D$17 | U16: =T16*0.1125*FeeCraft/100 | V16: =IF(OR(Q16="",R16=""),"",Q16+R16+U16) | W16: =IF(O16="","",O16*(1-TaxaVenda)) | X16: =IF(OR(V16="",W16=""),"",W16-V16) | Y16: =IF(X16="","",X16/V16)
A17: Soldado (Soldier)|Armadura|T6.3 | B17: Soldado (Soldier) | C17: Armadura | D17: T6.3 | E17: 6 | F17: 3 | G17: 16 | O17: =IF(COUNT(H17:N17)=0,"",MAX(H17:N17)) | P17: =IF(O17="","",INDEX($H$3:$N$3,MATCH(O17,H17:N17,0))) | Q17: =IF(Refino!$L$18="","",G17*Refino!$L$18*(1-RetCraft)) | R17: 0 | S17: - | T17: =G17*Refino!$D$18 | U17: =T17*0.1125*FeeCraft/100 | V17: =IF(OR(Q17="",R17=""),"",Q17+R17+U17) | W17: =IF(O17="","",O17*(1-TaxaVenda)) | X17: =IF(OR(V17="",W17=""),"",W17-V17) | Y17: =IF(X17="","",X17/V17)
A18: Soldado (Soldier)|Armadura|T6.4 | B18: Soldado (Soldier) | C18: Armadura | D18: T6.4 | E18: 6 | F18: 4 | G18: 16 | O18: =IF(COUNT(H18:N18)=0,"",MAX(H18:N18)) | P18: =IF(O18="","",INDEX($H$3:$N$3,MATCH(O18,H18:N18,0))) | Q18: =IF(Refino!$L$19="","",G18*Refino!$L$19*(1-RetCraft)) | R18: 0 | S18: - | T18: =G18*Refino!$D$19 | U18: =T18*0.1125*FeeCraft/100 | V18: =IF(OR(Q18="",R18=""),"",Q18+R18+U18) | W18: =IF(O18="","",O18*(1-TaxaVenda)) | X18: =IF(OR(V18="",W18=""),"",W18-V18) | Y18: =IF(X18="","",X18/V18)
A19: Soldado (Soldier)|Armadura|T7.0 | B19: Soldado (Soldier) | C19: Armadura | D19: T7.0 | E19: 7 | F19: 0 | G19: 16 | O19: =IF(COUNT(H19:N19)=0,"",MAX(H19:N19)) | P19: =IF(O19="","",INDEX($H$3:$N$3,MATCH(O19,H19:N19,0))) | Q19: =IF(Refino!$L$20="","",G19*Refino!$L$20*(1-RetCraft)) | R19: 0 | S19: - | T19: =G19*Refino!$D$20 | U19: =T19*0.1125*FeeCraft/100 | V19: =IF(OR(Q19="",R19=""),"",Q19+R19+U19) | W19: =IF(O19="","",O19*(1-TaxaVenda)) | X19: =IF(OR(V19="",W19=""),"",W19-V19) | Y19: =IF(X19="","",X19/V19)
A20: Soldado (Soldier)|Armadura|T7.1 | B20: Soldado (Soldier) | C20: Armadura | D20: T7.1 | E20: 7 | F20: 1 | G20: 16 | O20: =IF(COUNT(H20:N20)=0,"",MAX(H20:N20)) | P20: =IF(O20="","",INDEX($H$3:$N$3,MATCH(O20,H20:N20,0))) | Q20: =IF(Refino!$L$21="","",G20*Refino!$L$21*(1-RetCraft)) | R20: 0 | S20: - | T20: =G20*Refino!$D$21 | U20: =T20*0.1125*FeeCraft/100 | V20: =IF(OR(Q20="",R20=""),"",Q20+R20+U20) | W20: =IF(O20="","",O20*(1-TaxaVenda)) | X20: =IF(OR(V20="",W20=""),"",W20-V20) | Y20: =IF(X20="","",X20/V20)
A21: Soldado (Soldier)|Armadura|T7.2 | B21: Soldado (Soldier) | C21: Armadura | D21: T7.2 | E21: 7 | F21: 2 | G21: 16 | O21: =IF(COUNT(H21:N21)=0,"",MAX(H21:N21)) | P21: =IF(O21="","",INDEX($H$3:$N$3,MATCH(O21,H21:N21,0))) | Q21: =IF(Refino!$L$22="","",G21*Refino!$L$22*(1-RetCraft)) | R21: 0 | S21: - | T21: =G21*Refino!$D$22 | U21: =T21*0.1125*FeeCraft/100 | V21: =IF(OR(Q21="",R21=""),"",Q21+R21+U21) | W21: =IF(O21="","",O21*(1-TaxaVenda)) | X21: =IF(OR(V21="",W21=""),"",W21-V21) | Y21: =IF(X21="","",X21/V21)
A22: Soldado (Soldier)|Armadura|T7.3 | B22: Soldado (Soldier) | C22: Armadura | D22: T7.3 | E22: 7 | F22: 3 | G22: 16 | O22: =IF(COUNT(H22:N22)=0,"",MAX(H22:N22)) | P22: =IF(O22="","",INDEX($H$3:$N$3,MATCH(O22,H22:N22,0))) | Q22: =IF(Refino!$L$23="","",G22*Refino!$L$23*(1-RetCraft)) | R22: 0 | S22: - | T22: =G22*Refino!$D$23 | U22: =T22*0.1125*FeeCraft/100 | V22: =IF(OR(Q22="",R22=""),"",Q22+R22+U22) | W22: =IF(O22="","",O22*(1-TaxaVenda)) | X22: =IF(OR(V22="",W22=""),"",W22-V22) | Y22: =IF(X22="","",X22/V22)
A23: Soldado (Soldier)|Armadura|T7.4 | B23: Soldado (Soldier) | C23: Armadura | D23: T7.4 | E23: 7 | F23: 4 | G23: 16 | O23: =IF(COUNT(H23:N23)=0,"",MAX(H23:N23)) | P23: =IF(O23="","",INDEX($H$3:$N$3,MATCH(O23,H23:N23,0))) | Q23: =IF(Refino!$L$24="","",G23*Refino!$L$24*(1-RetCraft)) | R23: 0 | S23: - | T23: =G23*Refino!$D$24 | U23: =T23*0.1125*FeeCraft/100 | V23: =IF(OR(Q23="",R23=""),"",Q23+R23+U23) | W23: =IF(O23="","",O23*(1-TaxaVenda)) | X23: =IF(OR(V23="",W23=""),"",W23-V23) | Y23: =IF(X23="","",X23/V23)
A24: Soldado (Soldier)|Armadura|T8.0 | B24: Soldado (Soldier) | C24: Armadura | D24: T8.0 | E24: 8 | F24: 0 | G24: 16 | O24: =IF(COUNT(H24:N24)=0,"",MAX(H24:N24)) | P24: =IF(O24="","",INDEX($H$3:$N$3,MATCH(O24,H24:N24,0))) | Q24: =IF(Refino!$L$25="","",G24*Refino!$L$25*(1-RetCraft)) | R24: 0 | S24: - | T24: =G24*Refino!$D$25 | U24: =T24*0.1125*FeeCraft/100 | V24: =IF(OR(Q24="",R24=""),"",Q24+R24+U24) | W24: =IF(O24="","",O24*(1-TaxaVenda)) | X24: =IF(OR(V24="",W24=""),"",W24-V24) | Y24: =IF(X24="","",X24/V24)
A25: Soldado (Soldier)|Armadura|T8.1 | B25: Soldado (Soldier) | C25: Armadura | D25: T8.1 | E25: 8 | F25: 1 | G25: 16 | O25: =IF(COUNT(H25:N25)=0,"",MAX(H25:N25)) | P25: =IF(O25="","",INDEX($H$3:$N$3,MATCH(O25,H25:N25,0))) | Q25: =IF(Refino!$L$26="","",G25*Refino!$L$26*(1-RetCraft)) | R25: 0 | S25: - | T25: =G25*Refino!$D$26 | U25: =T25*0.1125*FeeCraft/100 | V25: =IF(OR(Q25="",R25=""),"",Q25+R25+U25) | W25: =IF(O25="","",O25*(1-TaxaVenda)) | X25: =IF(OR(V25="",W25=""),"",W25-V25) | Y25: =IF(X25="","",X25/V25)
A26: Soldado (Soldier)|Armadura|T8.2 | B26: Soldado (Soldier) | C26: Armadura | D26: T8.2 | E26: 8 | F26: 2 | G26: 16 | O26: =IF(COUNT(H26:N26)=0,"",MAX(H26:N26)) | P26: =IF(O26="","",INDEX($H$3:$N$3,MATCH(O26,H26:N26,0))) | Q26: =IF(Refino!$L$27="","",G26*Refino!$L$27*(1-RetCraft)) | R26: 0 | S26: - | T26: =G26*Refino!$D$27 | U26: =T26*0.1125*FeeCraft/100 | V26: =IF(OR(Q26="",R26=""),"",Q26+R26+U26) | W26: =IF(O26="","",O26*(1-TaxaVenda)) | X26: =IF(OR(V26="",W26=""),"",W26-V26) | Y26: =IF(X26="","",X26/V26)
A27: Soldado (Soldier)|Armadura|T8.3 | B27: Soldado (Soldier) | C27: Armadura | D27: T8.3 | E27: 8 | F27: 3 | G27: 16 | O27: =IF(COUNT(H27:N27)=0,"",MAX(H27:N27)) | P27: =IF(O27="","",INDEX($H$3:$N$3,MATCH(O27,H27:N27,0))) | Q27: =IF(Refino!$L$28="","",G27*Refino!$L$28*(1-RetCraft)) | R27: 0 | S27: - | T27: =G27*Refino!$D$28 | U27: =T27*0.1125*FeeCraft/100 | V27: =IF(OR(Q27="",R27=""),"",Q27+R27+U27) | W27: =IF(O27="","",O27*(1-TaxaVenda)) | X27: =IF(OR(V27="",W27=""),"",W27-V27) | Y27: =IF(X27="","",X27/V27)
A28: Soldado (Soldier)|Armadura|T8.4 | B28: Soldado (Soldier) | C28: Armadura | D28: T8.4 | E28: 8 | F28: 4 | G28: 16 | O28: =IF(COUNT(H28:N28)=0,"",MAX(H28:N28)) | P28: =IF(O28="","",INDEX($H$3:$N$3,MATCH(O28,H28:N28,0))) | Q28: =IF(Refino!$L$29="","",G28*Refino!$L$29*(1-RetCraft)) | R28: 0 | S28: - | T28: =G28*Refino!$D$29 | U28: =T28*0.1125*FeeCraft/100 | V28: =IF(OR(Q28="",R28=""),"",Q28+R28+U28) | W28: =IF(O28="","",O28*(1-TaxaVenda)) | X28: =IF(OR(V28="",W28=""),"",W28-V28) | Y28: =IF(X28="","",X28/V28)
A29: Soldado (Soldier)|Elmo|T4.0 | B29: Soldado (Soldier) | C29: Elmo | D29: T4.0 | E29: 4 | F29: 0 | G29: 8 | O29: =IF(COUNT(H29:N29)=0,"",MAX(H29:N29)) | P29: =IF(O29="","",INDEX($H$3:$N$3,MATCH(O29,H29:N29,0))) | Q29: =IF(Refino!$L$5="","",G29*Refino!$L$5*(1-RetCraft)) | R29: 0 | S29: - | T29: =G29*Refino!$D$5 | U29: =T29*0.1125*FeeCraft/100 | V29: =IF(OR(Q29="",R29=""),"",Q29+R29+U29) | W29: =IF(O29="","",O29*(1-TaxaVenda)) | X29: =IF(OR(V29="",W29=""),"",W29-V29) | Y29: =IF(X29="","",X29/V29)
A30: Soldado (Soldier)|Elmo|T4.1 | B30: Soldado (Soldier) | C30: Elmo | D30: T4.1 | E30: 4 | F30: 1 | G30: 8 | O30: =IF(COUNT(H30:N30)=0,"",MAX(H30:N30)) | P30: =IF(O30="","",INDEX($H$3:$N$3,MATCH(O30,H30:N30,0))) | Q30: =IF(Refino!$L$6="","",G30*Refino!$L$6*(1-RetCraft)) | R30: 0 | S30: - | T30: =G30*Refino!$D$6 | U30: =T30*0.1125*FeeCraft/100 | V30: =IF(OR(Q30="",R30=""),"",Q30+R30+U30) | W30: =IF(O30="","",O30*(1-TaxaVenda)) | X30: =IF(OR(V30="",W30=""),"",W30-V30) | Y30: =IF(X30="","",X30/V30)
A31: Soldado (Soldier)|Elmo|T4.2 | B31: Soldado (Soldier) | C31: Elmo | D31: T4.2 | E31: 4 | F31: 2 | G31: 8 | O31: =IF(COUNT(H31:N31)=0,"",MAX(H31:N31)) | P31: =IF(O31="","",INDEX($H$3:$N$3,MATCH(O31,H31:N31,0))) | Q31: =IF(Refino!$L$7="","",G31*Refino!$L$7*(1-RetCraft)) | R31: 0 | S31: - | T31: =G31*Refino!$D$7 | U31: =T31*0.1125*FeeCraft/100 | V31: =IF(OR(Q31="",R31=""),"",Q31+R31+U31) | W31: =IF(O31="","",O31*(1-TaxaVenda)) | X31: =IF(OR(V31="",W31=""),"",W31-V31) | Y31: =IF(X31="","",X31/V31)
A32: Soldado (Soldier)|Elmo|T4.3 | B32: Soldado (Soldier) | C32: Elmo | D32: T4.3 | E32: 4 | F32: 3 | G32: 8 | O32: =IF(COUNT(H32:N32)=0,"",MAX(H32:N32)) | P32: =IF(O32="","",INDEX($H$3:$N$3,MATCH(O32,H32:N32,0))) | Q32: =IF(Refino!$L$8="","",G32*Refino!$L$8*(1-RetCraft)) | R32: 0 | S32: - | T32: =G32*Refino!$D$8 | U32: =T32*0.1125*FeeCraft/100 | V32: =IF(OR(Q32="",R32=""),"",Q32+R32+U32) | W32: =IF(O32="","",O32*(1-TaxaVenda)) | X32: =IF(OR(V32="",W32=""),"",W32-V32) | Y32: =IF(X32="","",X32/V32)
A33: Soldado (Soldier)|Elmo|T4.4 | B33: Soldado (Soldier) | C33: Elmo | D33: T4.4 | E33: 4 | F33: 4 | G33: 8 | O33: =IF(COUNT(H33:N33)=0,"",MAX(H33:N33)) | P33: =IF(O33="","",INDEX($H$3:$N$3,MATCH(O33,H33:N33,0))) | Q33: =IF(Refino!$L$9="","",G33*Refino!$L$9*(1-RetCraft)) | R33: 0 | S33: - | T33: =G33*Refino!$D$9 | U33: =T33*0.1125*FeeCraft/100 | V33: =IF(OR(Q33="",R33=""),"",Q33+R33+U33) | W33: =IF(O33="","",O33*(1-TaxaVenda)) | X33: =IF(OR(V33="",W33=""),"",W33-V33) | Y33: =IF(X33="","",X33/V33)
A34: Soldado (Soldier)|Elmo|T5.0 | B34: Soldado (Soldier) | C34: Elmo | D34: T5.0 | E34: 5 | F34: 0 | G34: 8 | O34: =IF(COUNT(H34:N34)=0,"",MAX(H34:N34)) | P34: =IF(O34="","",INDEX($H$3:$N$3,MATCH(O34,H34:N34,0))) | Q34: =IF(Refino!$L$10="","",G34*Refino!$L$10*(1-RetCraft)) | R34: 0 | S34: - | T34: =G34*Refino!$D$10 | U34: =T34*0.1125*FeeCraft/100 | V34: =IF(OR(Q34="",R34=""),"",Q34+R34+U34) | W34: =IF(O34="","",O34*(1-TaxaVenda)) | X34: =IF(OR(V34="",W34=""),"",W34-V34) | Y34: =IF(X34="","",X34/V34)
A35: Soldado (Soldier)|Elmo|T5.1 | B35: Soldado (Soldier) | C35: Elmo | D35: T5.1 | E35: 5 | F35: 1 | G35: 8 | O35: =IF(COUNT(H35:N35)=0,"",MAX(H35:N35)) | P35: =IF(O35="","",INDEX($H$3:$N$3,MATCH(O35,H35:N35,0))) | Q35: =IF(Refino!$L$11="","",G35*Refino!$L$11*(1-RetCraft)) | R35: 0 | S35: - | T35: =G35*Refino!$D$11 | U35: =T35*0.1125*FeeCraft/100 | V35: =IF(OR(Q35="",R35=""),"",Q35+R35+U35) | W35: =IF(O35="","",O35*(1-TaxaVenda)) | X35: =IF(OR(V35="",W35=""),"",W35-V35) | Y35: =IF(X35="","",X35/V35)
A36: Soldado (Soldier)|Elmo|T5.2 | B36: Soldado (Soldier) | C36: Elmo | D36: T5.2 | E36: 5 | F36: 2 | G36: 8 | O36: =IF(COUNT(H36:N36)=0,"",MAX(H36:N36)) | P36: =IF(O36="","",INDEX($H$3:$N$3,MATCH(O36,H36:N36,0))) | Q36: =IF(Refino!$L$12="","",G36*Refino!$L$12*(1-RetCraft)) | R36: 0 | S36: - | T36: =G36*Refino!$D$12 | U36: =T36*0.1125*FeeCraft/100 | V36: =IF(OR(Q36="",R36=""),"",Q36+R36+U36) | W36: =IF(O36="","",O36*(1-TaxaVenda)) | X36: =IF(OR(V36="",W36=""),"",W36-V36) | Y36: =IF(X36="","",X36/V36)
A37: Soldado (Soldier)|Elmo|T5.3 | B37: Soldado (Soldier) | C37: Elmo | D37: T5.3 | E37: 5 | F37: 3 | G37: 8 | O37: =IF(COUNT(H37:N37)=0,"",MAX(H37:N37)) | P37: =IF(O37="","",INDEX($H$3:$N$3,MATCH(O37,H37:N37,0))) | Q37: =IF(Refino!$L$13="","",G37*Refino!$L$13*(1-RetCraft)) | R37: 0 | S37: - | T37: =G37*Refino!$D$13 | U37: =T37*0.1125*FeeCraft/100 | V37: =IF(OR(Q37="",R37=""),"",Q37+R37+U37) | W37: =IF(O37="","",O37*(1-TaxaVenda)) | X37: =IF(OR(V37="",W37=""),"",W37-V37) | Y37: =IF(X37="","",X37/V37)
A38: Soldado (Soldier)|Elmo|T5.4 | B38: Soldado (Soldier) | C38: Elmo | D38: T5.4 | E38: 5 | F38: 4 | G38: 8 | O38: =IF(COUNT(H38:N38)=0,"",MAX(H38:N38)) | P38: =IF(O38="","",INDEX($H$3:$N$3,MATCH(O38,H38:N38,0))) | Q38: =IF(Refino!$L$14="","",G38*Refino!$L$14*(1-RetCraft)) | R38: 0 | S38: - | T38: =G38*Refino!$D$14 | U38: =T38*0.1125*FeeCraft/100 | V38: =IF(OR(Q38="",R38=""),"",Q38+R38+U38) | W38: =IF(O38="","",O38*(1-TaxaVenda)) | X38: =IF(OR(V38="",W38=""),"",W38-V38) | Y38: =IF(X38="","",X38/V38)
A39: Soldado (Soldier)|Elmo|T6.0 | B39: Soldado (Soldier) | C39: Elmo | D39: T6.0 | E39: 6 | F39: 0 | G39: 8 | O39: =IF(COUNT(H39:N39)=0,"",MAX(H39:N39)) | P39: =IF(O39="","",INDEX($H$3:$N$3,MATCH(O39,H39:N39,0))) | Q39: =IF(Refino!$L$15="","",G39*Refino!$L$15*(1-RetCraft)) | R39: 0 | S39: - | T39: =G39*Refino!$D$15 | U39: =T39*0.1125*FeeCraft/100 | V39: =IF(OR(Q39="",R39=""),"",Q39+R39+U39) | W39: =IF(O39="","",O39*(1-TaxaVenda)) | X39: =IF(OR(V39="",W39=""),"",W39-V39) | Y39: =IF(X39="","",X39/V39)
A40: Soldado (Soldier)|Elmo|T6.1 | B40: Soldado (Soldier) | C40: Elmo | D40: T6.1 | E40: 6 | F40: 1 | G40: 8 | O40: =IF(COUNT(H40:N40)=0,"",MAX(H40:N40)) | P40: =IF(O40="","",INDEX($H$3:$N$3,MATCH(O40,H40:N40,0))) | Q40: =IF(Refino!$L$16="","",G40*Refino!$L$16*(1-RetCraft)) | R40: 0 | S40: - | T40: =G40*Refino!$D$16 | U40: =T40*0.1125*FeeCraft/100 | V40: =IF(OR(Q40="",R40=""),"",Q40+R40+U40) | W40: =IF(O40="","",O40*(1-TaxaVenda)) | X40: =IF(OR(V40="",W40=""),"",W40-V40) | Y40: =IF(X40="","",X40/V40)
A41: Soldado (Soldier)|Elmo|T6.2 | B41: Soldado (Soldier) | C41: Elmo | D41: T6.2 | E41: 6 | F41: 2 | G41: 8 | O41: =IF(COUNT(H41:N41)=0,"",MAX(H41:N41)) | P41: =IF(O41="","",INDEX($H$3:$N$3,MATCH(O41,H41:N41,0))) | Q41: =IF(Refino!$L$17="","",G41*Refino!$L$17*(1-RetCraft)) | R41: 0 | S41: - | T41: =G41*Refino!$D$17 | U41: =T41*0.1125*FeeCraft/100 | V41: =IF(OR(Q41="",R41=""),"",Q41+R41+U41) | W41: =IF(O41="","",O41*(1-TaxaVenda)) | X41: =IF(OR(V41="",W41=""),"",W41-V41) | Y41: =IF(X41="","",X41/V41)
A42: Soldado (Soldier)|Elmo|T6.3 | B42: Soldado (Soldier) | C42: Elmo | D42: T6.3 | E42: 6 | F42: 3 | G42: 8 | O42: =IF(COUNT(H42:N42)=0,"",MAX(H42:N42)) | P42: =IF(O42="","",INDEX($H$3:$N$3,MATCH(O42,H42:N42,0))) | Q42: =IF(Refino!$L$18="","",G42*Refino!$L$18*(1-RetCraft)) | R42: 0 | S42: - | T42: =G42*Refino!$D$18 | U42: =T42*0.1125*FeeCraft/100 | V42: =IF(OR(Q42="",R42=""),"",Q42+R42+U42) | W42: =IF(O42="","",O42*(1-TaxaVenda)) | X42: =IF(OR(V42="",W42=""),"",W42-V42) | Y42: =IF(X42="","",X42/V42)
A43: Soldado (Soldier)|Elmo|T6.4 | B43: Soldado (Soldier) | C43: Elmo | D43: T6.4 | E43: 6 | F43: 4 | G43: 8 | O43: =IF(COUNT(H43:N43)=0,"",MAX(H43:N43)) | P43: =IF(O43="","",INDEX($H$3:$N$3,MATCH(O43,H43:N43,0))) | Q43: =IF(Refino!$L$19="","",G43*Refino!$L$19*(1-RetCraft)) | R43: 0 | S43: - | T43: =G43*Refino!$D$19 | U43: =T43*0.1125*FeeCraft/100 | V43: =IF(OR(Q43="",R43=""),"",Q43+R43+U43) | W43: =IF(O43="","",O43*(1-TaxaVenda)) | X43: =IF(OR(V43="",W43=""),"",W43-V43) | Y43: =IF(X43="","",X43/V43)
A44: Soldado (Soldier)|Elmo|T7.0 | B44: Soldado (Soldier) | C44: Elmo | D44: T7.0 | E44: 7 | F44: 0 | G44: 8 | O44: =IF(COUNT(H44:N44)=0,"",MAX(H44:N44)) | P44: =IF(O44="","",INDEX($H$3:$N$3,MATCH(O44,H44:N44,0))) | Q44: =IF(Refino!$L$20="","",G44*Refino!$L$20*(1-RetCraft)) | R44: 0 | S44: - | T44: =G44*Refino!$D$20 | U44: =T44*0.1125*FeeCraft/100 | V44: =IF(OR(Q44="",R44=""),"",Q44+R44+U44) | W44: =IF(O44="","",O44*(1-TaxaVenda)) | X44: =IF(OR(V44="",W44=""),"",W44-V44) | Y44: =IF(X44="","",X44/V44)
A45: Soldado (Soldier)|Elmo|T7.1 | B45: Soldado (Soldier) | C45: Elmo | D45: T7.1 | E45: 7 | F45: 1 | G45: 8 | O45: =IF(COUNT(H45:N45)=0,"",MAX(H45:N45)) | P45: =IF(O45="","",INDEX($H$3:$N$3,MATCH(O45,H45:N45,0))) | Q45: =IF(Refino!$L$21="","",G45*Refino!$L$21*(1-RetCraft)) | R45: 0 | S45: - | T45: =G45*Refino!$D$21 | U45: =T45*0.1125*FeeCraft/100 | V45: =IF(OR(Q45="",R45=""),"",Q45+R45+U45) | W45: =IF(O45="","",O45*(1-TaxaVenda)) | X45: =IF(OR(V45="",W45=""),"",W45-V45) | Y45: =IF(X45="","",X45/V45)
A46: Soldado (Soldier)|Elmo|T7.2 | B46: Soldado (Soldier) | C46: Elmo | D46: T7.2 | E46: 7 | F46: 2 | G46: 8 | O46: =IF(COUNT(H46:N46)=0,"",MAX(H46:N46)) | P46: =IF(O46="","",INDEX($H$3:$N$3,MATCH(O46,H46:N46,0))) | Q46: =IF(Refino!$L$22="","",G46*Refino!$L$22*(1-RetCraft)) | R46: 0 | S46: - | T46: =G46*Refino!$D$22 | U46: =T46*0.1125*FeeCraft/100 | V46: =IF(OR(Q46="",R46=""),"",Q46+R46+U46) | W46: =IF(O46="","",O46*(1-TaxaVenda)) | X46: =IF(OR(V46="",W46=""),"",W46-V46) | Y46: =IF(X46="","",X46/V46)
A47: Soldado (Soldier)|Elmo|T7.3 | B47: Soldado (Soldier) | C47: Elmo | D47: T7.3 | E47: 7 | F47: 3 | G47: 8 | O47: =IF(COUNT(H47:N47)=0,"",MAX(H47:N47)) | P47: =IF(O47="","",INDEX($H$3:$N$3,MATCH(O47,H47:N47,0))) | Q47: =IF(Refino!$L$23="","",G47*Refino!$L$23*(1-RetCraft)) | R47: 0 | S47: - | T47: =G47*Refino!$D$23 | U47: =T47*0.1125*FeeCraft/100 | V47: =IF(OR(Q47="",R47=""),"",Q47+R47+U47) | W47: =IF(O47="","",O47*(1-TaxaVenda)) | X47: =IF(OR(V47="",W47=""),"",W47-V47) | Y47: =IF(X47="","",X47/V47)
A48: Soldado (Soldier)|Elmo|T7.4 | B48: Soldado (Soldier) | C48: Elmo | D48: T7.4 | E48: 7 | F48: 4 | G48: 8 | O48: =IF(COUNT(H48:N48)=0,"",MAX(H48:N48)) | P48: =IF(O48="","",INDEX($H$3:$N$3,MATCH(O48,H48:N48,0))) | Q48: =IF(Refino!$L$24="","",G48*Refino!$L$24*(1-RetCraft)) | R48: 0 | S48: - | T48: =G48*Refino!$D$24 | U48: =T48*0.1125*FeeCraft/100 | V48: =IF(OR(Q48="",R48=""),"",Q48+R48+U48) | W48: =IF(O48="","",O48*(1-TaxaVenda)) | X48: =IF(OR(V48="",W48=""),"",W48-V48) | Y48: =IF(X48="","",X48/V48)
A49: Soldado (Soldier)|Elmo|T8.0 | B49: Soldado (Soldier) | C49: Elmo | D49: T8.0 | E49: 8 | F49: 0 | G49: 8 | O49: =IF(COUNT(H49:N49)=0,"",MAX(H49:N49)) | P49: =IF(O49="","",INDEX($H$3:$N$3,MATCH(O49,H49:N49,0))) | Q49: =IF(Refino!$L$25="","",G49*Refino!$L$25*(1-RetCraft)) | R49: 0 | S49: - | T49: =G49*Refino!$D$25 | U49: =T49*0.1125*FeeCraft/100 | V49: =IF(OR(Q49="",R49=""),"",Q49+R49+U49) | W49: =IF(O49="","",O49*(1-TaxaVenda)) | X49: =IF(OR(V49="",W49=""),"",W49-V49) | Y49: =IF(X49="","",X49/V49)
A50: Soldado (Soldier)|Elmo|T8.1 | B50: Soldado (Soldier) | C50: Elmo | D50: T8.1 | E50: 8 | F50: 1 | G50: 8 | O50: =IF(COUNT(H50:N50)=0,"",MAX(H50:N50)) | P50: =IF(O50="","",INDEX($H$3:$N$3,MATCH(O50,H50:N50,0))) | Q50: =IF(Refino!$L$26="","",G50*Refino!$L$26*(1-RetCraft)) | R50: 0 | S50: - | T50: =G50*Refino!$D$26 | U50: =T50*0.1125*FeeCraft/100 | V50: =IF(OR(Q50="",R50=""),"",Q50+R50+U50) | W50: =IF(O50="","",O50*(1-TaxaVenda)) | X50: =IF(OR(V50="",W50=""),"",W50-V50) | Y50: =IF(X50="","",X50/V50)
A51: Soldado (Soldier)|Elmo|T8.2 | B51: Soldado (Soldier) | C51: Elmo | D51: T8.2 | E51: 8 | F51: 2 | G51: 8 | O51: =IF(COUNT(H51:N51)=0,"",MAX(H51:N51)) | P51: =IF(O51="","",INDEX($H$3:$N$3,MATCH(O51,H51:N51,0))) | Q51: =IF(Refino!$L$27="","",G51*Refino!$L$27*(1-RetCraft)) | R51: 0 | S51: - | T51: =G51*Refino!$D$27 | U51: =T51*0.1125*FeeCraft/100 | V51: =IF(OR(Q51="",R51=""),"",Q51+R51+U51) | W51: =IF(O51="","",O51*(1-TaxaVenda)) | X51: =IF(OR(V51="",W51=""),"",W51-V51) | Y51: =IF(X51="","",X51/V51)
A52: Soldado (Soldier)|Elmo|T8.3 | B52: Soldado (Soldier) | C52: Elmo | D52: T8.3 | E52: 8 | F52: 3 | G52: 8 | O52: =IF(COUNT(H52:N52)=0,"",MAX(H52:N52)) | P52: =IF(O52="","",INDEX($H$3:$N$3,MATCH(O52,H52:N52,0))) | Q52: =IF(Refino!$L$28="","",G52*Refino!$L$28*(1-RetCraft)) | R52: 0 | S52: - | T52: =G52*Refino!$D$28 | U52: =T52*0.1125*FeeCraft/100 | V52: =IF(OR(Q52="",R52=""),"",Q52+R52+U52) | W52: =IF(O52="","",O52*(1-TaxaVenda)) | X52: =IF(OR(V52="",W52=""),"",W52-V52) | Y52: =IF(X52="","",X52/V52)
A53: Soldado (Soldier)|Elmo|T8.4 | B53: Soldado (Soldier) | C53: Elmo | D53: T8.4 | E53: 8 | F53: 4 | G53: 8 | O53: =IF(COUNT(H53:N53)=0,"",MAX(H53:N53)) | P53: =IF(O53="","",INDEX($H$3:$N$3,MATCH(O53,H53:N53,0))) | Q53: =IF(Refino!$L$29="","",G53*Refino!$L$29*(1-RetCraft)) | R53: 0 | S53: - | T53: =G53*Refino!$D$29 | U53: =T53*0.1125*FeeCraft/100 | V53: =IF(OR(Q53="",R53=""),"",Q53+R53+U53) | W53: =IF(O53="","",O53*(1-TaxaVenda)) | X53: =IF(OR(V53="",W53=""),"",W53-V53) | Y53: =IF(X53="","",X53/V53)
A54: Soldado (Soldier)|Botas|T4.0 | B54: Soldado (Soldier) | C54: Botas | D54: T4.0 | E54: 4 | F54: 0 | G54: 8 | O54: =IF(COUNT(H54:N54)=0,"",MAX(H54:N54)) | P54: =IF(O54="","",INDEX($H$3:$N$3,MATCH(O54,H54:N54,0))) | Q54: =IF(Refino!$L$5="","",G54*Refino!$L$5*(1-RetCraft)) | R54: 0 | S54: - | T54: =G54*Refino!$D$5 | U54: =T54*0.1125*FeeCraft/100 | V54: =IF(OR(Q54="",R54=""),"",Q54+R54+U54) | W54: =IF(O54="","",O54*(1-TaxaVenda)) | X54: =IF(OR(V54="",W54=""),"",W54-V54) | Y54: =IF(X54="","",X54/V54)
A55: Soldado (Soldier)|Botas|T4.1 | B55: Soldado (Soldier) | C55: Botas | D55: T4.1 | E55: 4 | F55: 1 | G55: 8 | O55: =IF(COUNT(H55:N55)=0,"",MAX(H55:N55)) | P55: =IF(O55="","",INDEX($H$3:$N$3,MATCH(O55,H55:N55,0))) | Q55: =IF(Refino!$L$6="","",G55*Refino!$L$6*(1-RetCraft)) | R55: 0 | S55: - | T55: =G55*Refino!$D$6 | U55: =T55*0.1125*FeeCraft/100 | V55: =IF(OR(Q55="",R55=""),"",Q55+R55+U55) | W55: =IF(O55="","",O55*(1-TaxaVenda)) | X55: =IF(OR(V55="",W55=""),"",W55-V55) | Y55: =IF(X55="","",X55/V55)
A56: Soldado (Soldier)|Botas|T4.2 | B56: Soldado (Soldier) | C56: Botas | D56: T4.2 | E56: 4 | F56: 2 | G56: 8 | O56: =IF(COUNT(H56:N56)=0,"",MAX(H56:N56)) | P56: =IF(O56="","",INDEX($H$3:$N$3,MATCH(O56,H56:N56,0))) | Q56: =IF(Refino!$L$7="","",G56*Refino!$L$7*(1-RetCraft)) | R56: 0 | S56: - | T56: =G56*Refino!$D$7 | U56: =T56*0.1125*FeeCraft/100 | V56: =IF(OR(Q56="",R56=""),"",Q56+R56+U56) | W56: =IF(O56="","",O56*(1-TaxaVenda)) | X56: =IF(OR(V56="",W56=""),"",W56-V56) | Y56: =IF(X56="","",X56/V56)
A57: Soldado (Soldier)|Botas|T4.3 | B57: Soldado (Soldier) | C57: Botas | D57: T4.3 | E57: 4 | F57: 3 | G57: 8 | O57: =IF(COUNT(H57:N57)=0,"",MAX(H57:N57)) | P57: =IF(O57="","",INDEX($H$3:$N$3,MATCH(O57,H57:N57,0))) | Q57: =IF(Refino!$L$8="","",G57*Refino!$L$8*(1-RetCraft)) | R57: 0 | S57: - | T57: =G57*Refino!$D$8 | U57: =T57*0.1125*FeeCraft/100 | V57: =IF(OR(Q57="",R57=""),"",Q57+R57+U57) | W57: =IF(O57="","",O57*(1-TaxaVenda)) | X57: =IF(OR(V57="",W57=""),"",W57-V57) | Y57: =IF(X57="","",X57/V57)
A58: Soldado (Soldier)|Botas|T4.4 | B58: Soldado (Soldier) | C58: Botas | D58: T4.4 | E58: 4 | F58: 4 | G58: 8 | O58: =IF(COUNT(H58:N58)=0,"",MAX(H58:N58)) | P58: =IF(O58="","",INDEX($H$3:$N$3,MATCH(O58,H58:N58,0))) | Q58: =IF(Refino!$L$9="","",G58*Refino!$L$9*(1-RetCraft)) | R58: 0 | S58: - | T58: =G58*Refino!$D$9 | U58: =T58*0.1125*FeeCraft/100 | V58: =IF(OR(Q58="",R58=""),"",Q58+R58+U58) | W58: =IF(O58="","",O58*(1-TaxaVenda)) | X58: =IF(OR(V58="",W58=""),"",W58-V58) | Y58: =IF(X58="","",X58/V58)
A59: Soldado (Soldier)|Botas|T5.0 | B59: Soldado (Soldier) | C59: Botas | D59: T5.0 | E59: 5 | F59: 0 | G59: 8 | O59: =IF(COUNT(H59:N59)=0,"",MAX(H59:N59)) | P59: =IF(O59="","",INDEX($H$3:$N$3,MATCH(O59,H59:N59,0))) | Q59: =IF(Refino!$L$10="","",G59*Refino!$L$10*(1-RetCraft)) | R59: 0 | S59: - | T59: =G59*Refino!$D$10 | U59: =T59*0.1125*FeeCraft/100 | V59: =IF(OR(Q59="",R59=""),"",Q59+R59+U59) | W59: =IF(O59="","",O59*(1-TaxaVenda)) | X59: =IF(OR(V59="",W59=""),"",W59-V59) | Y59: =IF(X59="","",X59/V59)
A60: Soldado (Soldier)|Botas|T5.1 | B60: Soldado (Soldier) | C60: Botas | D60: T5.1 | E60: 5 | F60: 1 | G60: 8 | O60: =IF(COUNT(H60:N60)=0,"",MAX(H60:N60)) | P60: =IF(O60="","",INDEX($H$3:$N$3,MATCH(O60,H60:N60,0))) | Q60: =IF(Refino!$L$11="","",G60*Refino!$L$11*(1-RetCraft)) | R60: 0 | S60: - | T60: =G60*Refino!$D$11 | U60: =T60*0.1125*FeeCraft/100 | V60: =IF(OR(Q60="",R60=""),"",Q60+R60+U60) | W60: =IF(O60="","",O60*(1-TaxaVenda)) | X60: =IF(OR(V60="",W60=""),"",W60-V60) | Y60: =IF(X60="","",X60/V60)
A61: Soldado (Soldier)|Botas|T5.2 | B61: Soldado (Soldier) | C61: Botas | D61: T5.2 | E61: 5 | F61: 2 | G61: 8 | O61: =IF(COUNT(H61:N61)=0,"",MAX(H61:N61)) | P61: =IF(O61="","",INDEX($H$3:$N$3,MATCH(O61,H61:N61,0))) | Q61: =IF(Refino!$L$12="","",G61*Refino!$L$12*(1-RetCraft)) | R61: 0 | S61: - | T61: =G61*Refino!$D$12 | U61: =T61*0.1125*FeeCraft/100 | V61: =IF(OR(Q61="",R61=""),"",Q61+R61+U61) | W61: =IF(O61="","",O61*(1-TaxaVenda)) | X61: =IF(OR(V61="",W61=""),"",W61-V61) | Y61: =IF(X61="","",X61/V61)
A62: Soldado (Soldier)|Botas|T5.3 | B62: Soldado (Soldier) | C62: Botas | D62: T5.3 | E62: 5 | F62: 3 | G62: 8 | O62: =IF(COUNT(H62:N62)=0,"",MAX(H62:N62)) | P62: =IF(O62="","",INDEX($H$3:$N$3,MATCH(O62,H62:N62,0))) | Q62: =IF(Refino!$L$13="","",G62*Refino!$L$13*(1-RetCraft)) | R62: 0 | S62: - | T62: =G62*Refino!$D$13 | U62: =T62*0.1125*FeeCraft/100 | V62: =IF(OR(Q62="",R62=""),"",Q62+R62+U62) | W62: =IF(O62="","",O62*(1-TaxaVenda)) | X62: =IF(OR(V62="",W62=""),"",W62-V62) | Y62: =IF(X62="","",X62/V62)
A63: Soldado (Soldier)|Botas|T5.4 | B63: Soldado (Soldier) | C63: Botas | D63: T5.4 | E63: 5 | F63: 4 | G63: 8 | O63: =IF(COUNT(H63:N63)=0,"",MAX(H63:N63)) | P63: =IF(O63="","",INDEX($H$3:$N$3,MATCH(O63,H63:N63,0))) | Q63: =IF(Refino!$L$14="","",G63*Refino!$L$14*(1-RetCraft)) | R63: 0 | S63: - | T63: =G63*Refino!$D$14 | U63: =T63*0.1125*FeeCraft/100 | V63: =IF(OR(Q63="",R63=""),"",Q63+R63+U63) | W63: =IF(O63="","",O63*(1-TaxaVenda)) | X63: =IF(OR(V63="",W63=""),"",W63-V63) | Y63: =IF(X63="","",X63/V63)
A64: Soldado (Soldier)|Botas|T6.0 | B64: Soldado (Soldier) | C64: Botas | D64: T6.0 | E64: 6 | F64: 0 | G64: 8 | O64: =IF(COUNT(H64:N64)=0,"",MAX(H64:N64)) | P64: =IF(O64="","",INDEX($H$3:$N$3,MATCH(O64,H64:N64,0))) | Q64: =IF(Refino!$L$15="","",G64*Refino!$L$15*(1-RetCraft)) | R64: 0 | S64: - | T64: =G64*Refino!$D$15 | U64: =T64*0.1125*FeeCraft/100 | V64: =IF(OR(Q64="",R64=""),"",Q64+R64+U64) | W64: =IF(O64="","",O64*(1-TaxaVenda)) | X64: =IF(OR(V64="",W64=""),"",W64-V64) | Y64: =IF(X64="","",X64/V64)
A65: Soldado (Soldier)|Botas|T6.1 | B65: Soldado (Soldier) | C65: Botas | D65: T6.1 | E65: 6 | F65: 1 | G65: 8 | O65: =IF(COUNT(H65:N65)=0,"",MAX(H65:N65)) | P65: =IF(O65="","",INDEX($H$3:$N$3,MATCH(O65,H65:N65,0))) | Q65: =IF(Refino!$L$16="","",G65*Refino!$L$16*(1-RetCraft)) | R65: 0 | S65: - | T65: =G65*Refino!$D$16 | U65: =T65*0.1125*FeeCraft/100 | V65: =IF(OR(Q65="",R65=""),"",Q65+R65+U65) | W65: =IF(O65="","",O65*(1-TaxaVenda)) | X65: =IF(OR(V65="",W65=""),"",W65-V65) | Y65: =IF(X65="","",X65/V65)
A66: Soldado (Soldier)|Botas|T6.2 | B66: Soldado (Soldier) | C66: Botas | D66: T6.2 | E66: 6 | F66: 2 | G66: 8 | O66: =IF(COUNT(H66:N66)=0,"",MAX(H66:N66)) | P66: =IF(O66="","",INDEX($H$3:$N$3,MATCH(O66,H66:N66,0))) | Q66: =IF(Refino!$L$17="","",G66*Refino!$L$17*(1-RetCraft)) | R66: 0 | S66: - | T66: =G66*Refino!$D$17 | U66: =T66*0.1125*FeeCraft/100 | V66: =IF(OR(Q66="",R66=""),"",Q66+R66+U66) | W66: =IF(O66="","",O66*(1-TaxaVenda)) | X66: =IF(OR(V66="",W66=""),"",W66-V66) | Y66: =IF(X66="","",X66/V66)
A67: Soldado (Soldier)|Botas|T6.3 | B67: Soldado (Soldier) | C67: Botas | D67: T6.3 | E67: 6 | F67: 3 | G67: 8 | O67: =IF(COUNT(H67:N67)=0,"",MAX(H67:N67)) | P67: =IF(O67="","",INDEX($H$3:$N$3,MATCH(O67,H67:N67,0))) | Q67: =IF(Refino!$L$18="","",G67*Refino!$L$18*(1-RetCraft)) | R67: 0 | S67: - | T67: =G67*Refino!$D$18 | U67: =T67*0.1125*FeeCraft/100 | V67: =IF(OR(Q67="",R67=""),"",Q67+R67+U67) | W67: =IF(O67="","",O67*(1-TaxaVenda)) | X67: =IF(OR(V67="",W67=""),"",W67-V67) | Y67: =IF(X67="","",X67/V67)
A68: Soldado (Soldier)|Botas|T6.4 | B68: Soldado (Soldier) | C68: Botas | D68: T6.4 | E68: 6 | F68: 4 | G68: 8 | O68: =IF(COUNT(H68:N68)=0,"",MAX(H68:N68)) | P68: =IF(O68="","",INDEX($H$3:$N$3,MATCH(O68,H68:N68,0))) | Q68: =IF(Refino!$L$19="","",G68*Refino!$L$19*(1-RetCraft)) | R68: 0 | S68: - | T68: =G68*Refino!$D$19 | U68: =T68*0.1125*FeeCraft/100 | V68: =IF(OR(Q68="",R68=""),"",Q68+R68+U68) | W68: =IF(O68="","",O68*(1-TaxaVenda)) | X68: =IF(OR(V68="",W68=""),"",W68-V68) | Y68: =IF(X68="","",X68/V68)
A69: Soldado (Soldier)|Botas|T7.0 | B69: Soldado (Soldier) | C69: Botas | D69: T7.0 | E69: 7 | F69: 0 | G69: 8 | O69: =IF(COUNT(H69:N69)=0,"",MAX(H69:N69)) | P69: =IF(O69="","",INDEX($H$3:$N$3,MATCH(O69,H69:N69,0))) | Q69: =IF(Refino!$L$20="","",G69*Refino!$L$20*(1-RetCraft)) | R69: 0 | S69: - | T69: =G69*Refino!$D$20 | U69: =T69*0.1125*FeeCraft/100 | V69: =IF(OR(Q69="",R69=""),"",Q69+R69+U69) | W69: =IF(O69="","",O69*(1-TaxaVenda)) | X69: =IF(OR(V69="",W69=""),"",W69-V69) | Y69: =IF(X69="","",X69/V69)
A70: Soldado (Soldier)|Botas|T7.1 | B70: Soldado (Soldier) | C70: Botas | D70: T7.1 | E70: 7 | F70: 1 | G70: 8 | O70: =IF(COUNT(H70:N70)=0,"",MAX(H70:N70)) | P70: =IF(O70="","",INDEX($H$3:$N$3,MATCH(O70,H70:N70,0))) | Q70: =IF(Refino!$L$21="","",G70*Refino!$L$21*(1-RetCraft)) | R70: 0 | S70: - | T70: =G70*Refino!$D$21 | U70: =T70*0.1125*FeeCraft/100 | V70: =IF(OR(Q70="",R70=""),"",Q70+R70+U70) | W70: =IF(O70="","",O70*(1-TaxaVenda)) | X70: =IF(OR(V70="",W70=""),"",W70-V70) | Y70: =IF(X70="","",X70/V70)
A71: Soldado (Soldier)|Botas|T7.2 | B71: Soldado (Soldier) | C71: Botas | D71: T7.2 | E71: 7 | F71: 2 | G71: 8 | O71: =IF(COUNT(H71:N71)=0,"",MAX(H71:N71)) | P71: =IF(O71="","",INDEX($H$3:$N$3,MATCH(O71,H71:N71,0))) | Q71: =IF(Refino!$L$22="","",G71*Refino!$L$22*(1-RetCraft)) | R71: 0 | S71: - | T71: =G71*Refino!$D$22 | U71: =T71*0.1125*FeeCraft/100 | V71: =IF(OR(Q71="",R71=""),"",Q71+R71+U71) | W71: =IF(O71="","",O71*(1-TaxaVenda)) | X71: =IF(OR(V71="",W71=""),"",W71-V71) | Y71: =IF(X71="","",X71/V71)
A72: Soldado (Soldier)|Botas|T7.3 | B72: Soldado (Soldier) | C72: Botas | D72: T7.3 | E72: 7 | F72: 3 | G72: 8 | O72: =IF(COUNT(H72:N72)=0,"",MAX(H72:N72)) | P72: =IF(O72="","",INDEX($H$3:$N$3,MATCH(O72,H72:N72,0))) | Q72: =IF(Refino!$L$23="","",G72*Refino!$L$23*(1-RetCraft)) | R72: 0 | S72: - | T72: =G72*Refino!$D$23 | U72: =T72*0.1125*FeeCraft/100 | V72: =IF(OR(Q72="",R72=""),"",Q72+R72+U72) | W72: =IF(O72="","",O72*(1-TaxaVenda)) | X72: =IF(OR(V72="",W72=""),"",W72-V72) | Y72: =IF(X72="","",X72/V72)
A73: Soldado (Soldier)|Botas|T7.4 | B73: Soldado (Soldier) | C73: Botas | D73: T7.4 | E73: 7 | F73: 4 | G73: 8 | O73: =IF(COUNT(H73:N73)=0,"",MAX(H73:N73)) | P73: =IF(O73="","",INDEX($H$3:$N$3,MATCH(O73,H73:N73,0))) | Q73: =IF(Refino!$L$24="","",G73*Refino!$L$24*(1-RetCraft)) | R73: 0 | S73: - | T73: =G73*Refino!$D$24 | U73: =T73*0.1125*FeeCraft/100 | V73: =IF(OR(Q73="",R73=""),"",Q73+R73+U73) | W73: =IF(O73="","",O73*(1-TaxaVenda)) | X73: =IF(OR(V73="",W73=""),"",W73-V73) | Y73: =IF(X73="","",X73/V73)
A74: Soldado (Soldier)|Botas|T8.0 | B74: Soldado (Soldier) | C74: Botas | D74: T8.0 | E74: 8 | F74: 0 | G74: 8 | O74: =IF(COUNT(H74:N74)=0,"",MAX(H74:N74)) | P74: =IF(O74="","",INDEX($H$3:$N$3,MATCH(O74,H74:N74,0))) | Q74: =IF(Refino!$L$25="","",G74*Refino!$L$25*(1-RetCraft)) | R74: 0 | S74: - | T74: =G74*Refino!$D$25 | U74: =T74*0.1125*FeeCraft/100 | V74: =IF(OR(Q74="",R74=""),"",Q74+R74+U74) | W74: =IF(O74="","",O74*(1-TaxaVenda)) | X74: =IF(OR(V74="",W74=""),"",W74-V74) | Y74: =IF(X74="","",X74/V74)
A75: Soldado (Soldier)|Botas|T8.1 | B75: Soldado (Soldier) | C75: Botas | D75: T8.1 | E75: 8 | F75: 1 | G75: 8 | O75: =IF(COUNT(H75:N75)=0,"",MAX(H75:N75)) | P75: =IF(O75="","",INDEX($H$3:$N$3,MATCH(O75,H75:N75,0))) | Q75: =IF(Refino!$L$26="","",G75*Refino!$L$26*(1-RetCraft)) | R75: 0 | S75: - | T75: =G75*Refino!$D$26 | U75: =T75*0.1125*FeeCraft/100 | V75: =IF(OR(Q75="",R75=""),"",Q75+R75+U75) | W75: =IF(O75="","",O75*(1-TaxaVenda)) | X75: =IF(OR(V75="",W75=""),"",W75-V75) | Y75: =IF(X75="","",X75/V75)
A76: Soldado (Soldier)|Botas|T8.2 | B76: Soldado (Soldier) | C76: Botas | D76: T8.2 | E76: 8 | F76: 2 | G76: 8 | O76: =IF(COUNT(H76:N76)=0,"",MAX(H76:N76)) | P76: =IF(O76="","",INDEX($H$3:$N$3,MATCH(O76,H76:N76,0))) | Q76: =IF(Refino!$L$27="","",G76*Refino!$L$27*(1-RetCraft)) | R76: 0 | S76: - | T76: =G76*Refino!$D$27 | U76: =T76*0.1125*FeeCraft/100 | V76: =IF(OR(Q76="",R76=""),"",Q76+R76+U76) | W76: =IF(O76="","",O76*(1-TaxaVenda)) | X76: =IF(OR(V76="",W76=""),"",W76-V76) | Y76: =IF(X76="","",X76/V76)
A77: Soldado (Soldier)|Botas|T8.3 | B77: Soldado (Soldier) | C77: Botas | D77: T8.3 | E77: 8 | F77: 3 | G77: 8 | O77: =IF(COUNT(H77:N77)=0,"",MAX(H77:N77)) | P77: =IF(O77="","",INDEX($H$3:$N$3,MATCH(O77,H77:N77,0))) | Q77: =IF(Refino!$L$28="","",G77*Refino!$L$28*(1-RetCraft)) | R77: 0 | S77: - | T77: =G77*Refino!$D$28 | U77: =T77*0.1125*FeeCraft/100 | V77: =IF(OR(Q77="",R77=""),"",Q77+R77+U77) | W77: =IF(O77="","",O77*(1-TaxaVenda)) | X77: =IF(OR(V77="",W77=""),"",W77-V77) | Y77: =IF(X77="","",X77/V77)
A78: Soldado (Soldier)|Botas|T8.4 | B78: Soldado (Soldier) | C78: Botas | D78: T8.4 | E78: 8 | F78: 4 | G78: 8 | O78: =IF(COUNT(H78:N78)=0,"",MAX(H78:N78)) | P78: =IF(O78="","",INDEX($H$3:$N$3,MATCH(O78,H78:N78,0))) | Q78: =IF(Refino!$L$29="","",G78*Refino!$L$29*(1-RetCraft)) | R78: 0 | S78: - | T78: =G78*Refino!$D$29 | U78: =T78*0.1125*FeeCraft/100 | V78: =IF(OR(Q78="",R78=""),"",Q78+R78+U78) | W78: =IF(O78="","",O78*(1-TaxaVenda)) | X78: =IF(OR(V78="",W78=""),"",W78-V78) | Y78: =IF(X78="","",X78/V78)
A79: Cavaleiro (Knight)|Armadura|T4.0 | B79: Cavaleiro (Knight) | C79: Armadura | D79: T4.0 | E79: 4 | F79: 0 | G79: 16 | O79: =IF(COUNT(H79:N79)=0,"",MAX(H79:N79)) | P79: =IF(O79="","",INDEX($H$3:$N$3,MATCH(O79,H79:N79,0))) | Q79: =IF(Refino!$L$5="","",G79*Refino!$L$5*(1-RetCraft)) | R79: 0 | S79: - | T79: =G79*Refino!$D$5 | U79: =T79*0.1125*FeeCraft/100 | V79: =IF(OR(Q79="",R79=""),"",Q79+R79+U79) | W79: =IF(O79="","",O79*(1-TaxaVenda)) | X79: =IF(OR(V79="",W79=""),"",W79-V79) | Y79: =IF(X79="","",X79/V79)
A80: Cavaleiro (Knight)|Armadura|T4.1 | B80: Cavaleiro (Knight) | C80: Armadura | D80: T4.1 | E80: 4 | F80: 1 | G80: 16 | O80: =IF(COUNT(H80:N80)=0,"",MAX(H80:N80)) | P80: =IF(O80="","",INDEX($H$3:$N$3,MATCH(O80,H80:N80,0))) | Q80: =IF(Refino!$L$6="","",G80*Refino!$L$6*(1-RetCraft)) | R80: 0 | S80: - | T80: =G80*Refino!$D$6 | U80: =T80*0.1125*FeeCraft/100 | V80: =IF(OR(Q80="",R80=""),"",Q80+R80+U80) | W80: =IF(O80="","",O80*(1-TaxaVenda)) | X80: =IF(OR(V80="",W80=""),"",W80-V80) | Y80: =IF(X80="","",X80/V80)
A81: Cavaleiro (Knight)|Armadura|T4.2 | B81: Cavaleiro (Knight) | C81: Armadura | D81: T4.2 | E81: 4 | F81: 2 | G81: 16 | O81: =IF(COUNT(H81:N81)=0,"",MAX(H81:N81)) | P81: =IF(O81="","",INDEX($H$3:$N$3,MATCH(O81,H81:N81,0))) | Q81: =IF(Refino!$L$7="","",G81*Refino!$L$7*(1-RetCraft)) | R81: 0 | S81: - | T81: =G81*Refino!$D$7 | U81: =T81*0.1125*FeeCraft/100 | V81: =IF(OR(Q81="",R81=""),"",Q81+R81+U81) | W81: =IF(O81="","",O81*(1-TaxaVenda)) | X81: =IF(OR(V81="",W81=""),"",W81-V81) | Y81: =IF(X81="","",X81/V81)
A82: Cavaleiro (Knight)|Armadura|T4.3 | B82: Cavaleiro (Knight) | C82: Armadura | D82: T4.3 | E82: 4 | F82: 3 | G82: 16 | O82: =IF(COUNT(H82:N82)=0,"",MAX(H82:N82)) | P82: =IF(O82="","",INDEX($H$3:$N$3,MATCH(O82,H82:N82,0))) | Q82: =IF(Refino!$L$8="","",G82*Refino!$L$8*(1-RetCraft)) | R82: 0 | S82: - | T82: =G82*Refino!$D$8 | U82: =T82*0.1125*FeeCraft/100 | V82: =IF(OR(Q82="",R82=""),"",Q82+R82+U82) | W82: =IF(O82="","",O82*(1-TaxaVenda)) | X82: =IF(OR(V82="",W82=""),"",W82-V82) | Y82: =IF(X82="","",X82/V82)
A83: Cavaleiro (Knight)|Armadura|T4.4 | B83: Cavaleiro (Knight) | C83: Armadura | D83: T4.4 | E83: 4 | F83: 4 | G83: 16 | O83: =IF(COUNT(H83:N83)=0,"",MAX(H83:N83)) | P83: =IF(O83="","",INDEX($H$3:$N$3,MATCH(O83,H83:N83,0))) | Q83: =IF(Refino!$L$9="","",G83*Refino!$L$9*(1-RetCraft)) | R83: 0 | S83: - | T83: =G83*Refino!$D$9 | U83: =T83*0.1125*FeeCraft/100 | V83: =IF(OR(Q83="",R83=""),"",Q83+R83+U83) | W83: =IF(O83="","",O83*(1-TaxaVenda)) | X83: =IF(OR(V83="",W83=""),"",W83-V83) | Y83: =IF(X83="","",X83/V83)
A84: Cavaleiro (Knight)|Armadura|T5.0 | B84: Cavaleiro (Knight) | C84: Armadura | D84: T5.0 | E84: 5 | F84: 0 | G84: 16 | O84: =IF(COUNT(H84:N84)=0,"",MAX(H84:N84)) | P84: =IF(O84="","",INDEX($H$3:$N$3,MATCH(O84,H84:N84,0))) | Q84: =IF(Refino!$L$10="","",G84*Refino!$L$10*(1-RetCraft)) | R84: 0 | S84: - | T84: =G84*Refino!$D$10 | U84: =T84*0.1125*FeeCraft/100 | V84: =IF(OR(Q84="",R84=""),"",Q84+R84+U84) | W84: =IF(O84="","",O84*(1-TaxaVenda)) | X84: =IF(OR(V84="",W84=""),"",W84-V84) | Y84: =IF(X84="","",X84/V84)
A85: Cavaleiro (Knight)|Armadura|T5.1 | B85: Cavaleiro (Knight) | C85: Armadura | D85: T5.1 | E85: 5 | F85: 1 | G85: 16 | O85: =IF(COUNT(H85:N85)=0,"",MAX(H85:N85)) | P85: =IF(O85="","",INDEX($H$3:$N$3,MATCH(O85,H85:N85,0))) | Q85: =IF(Refino!$L$11="","",G85*Refino!$L$11*(1-RetCraft)) | R85: 0 | S85: - | T85: =G85*Refino!$D$11 | U85: =T85*0.1125*FeeCraft/100 | V85: =IF(OR(Q85="",R85=""),"",Q85+R85+U85) | W85: =IF(O85="","",O85*(1-TaxaVenda)) | X85: =IF(OR(V85="",W85=""),"",W85-V85) | Y85: =IF(X85="","",X85/V85)
A86: Cavaleiro (Knight)|Armadura|T5.2 | B86: Cavaleiro (Knight) | C86: Armadura | D86: T5.2 | E86: 5 | F86: 2 | G86: 16 | O86: =IF(COUNT(H86:N86)=0,"",MAX(H86:N86)) | P86: =IF(O86="","",INDEX($H$3:$N$3,MATCH(O86,H86:N86,0))) | Q86: =IF(Refino!$L$12="","",G86*Refino!$L$12*(1-RetCraft)) | R86: 0 | S86: - | T86: =G86*Refino!$D$12 | U86: =T86*0.1125*FeeCraft/100 | V86: =IF(OR(Q86="",R86=""),"",Q86+R86+U86) | W86: =IF(O86="","",O86*(1-TaxaVenda)) | X86: =IF(OR(V86="",W86=""),"",W86-V86) | Y86: =IF(X86="","",X86/V86)
A87: Cavaleiro (Knight)|Armadura|T5.3 | B87: Cavaleiro (Knight) | C87: Armadura | D87: T5.3 | E87: 5 | F87: 3 | G87: 16 | O87: =IF(COUNT(H87:N87)=0,"",MAX(H87:N87)) | P87: =IF(O87="","",INDEX($H$3:$N$3,MATCH(O87,H87:N87,0))) | Q87: =IF(Refino!$L$13="","",G87*Refino!$L$13*(1-RetCraft)) | R87: 0 | S87: - | T87: =G87*Refino!$D$13 | U87: =T87*0.1125*FeeCraft/100 | V87: =IF(OR(Q87="",R87=""),"",Q87+R87+U87) | W87: =IF(O87="","",O87*(1-TaxaVenda)) | X87: =IF(OR(V87="",W87=""),"",W87-V87) | Y87: =IF(X87="","",X87/V87)
A88: Cavaleiro (Knight)|Armadura|T5.4 | B88: Cavaleiro (Knight) | C88: Armadura | D88: T5.4 | E88: 5 | F88: 4 | G88: 16 | O88: =IF(COUNT(H88:N88)=0,"",MAX(H88:N88)) | P88: =IF(O88="","",INDEX($H$3:$N$3,MATCH(O88,H88:N88,0))) | Q88: =IF(Refino!$L$14="","",G88*Refino!$L$14*(1-RetCraft)) | R88: 0 | S88: - | T88: =G88*Refino!$D$14 | U88: =T88*0.1125*FeeCraft/100 | V88: =IF(OR(Q88="",R88=""),"",Q88+R88+U88) | W88: =IF(O88="","",O88*(1-TaxaVenda)) | X88: =IF(OR(V88="",W88=""),"",W88-V88) | Y88: =IF(X88="","",X88/V88)
A89: Cavaleiro (Knight)|Armadura|T6.0 | B89: Cavaleiro (Knight) | C89: Armadura | D89: T6.0 | E89: 6 | F89: 0 | G89: 16 | O89: =IF(COUNT(H89:N89)=0,"",MAX(H89:N89)) | P89: =IF(O89="","",INDEX($H$3:$N$3,MATCH(O89,H89:N89,0))) | Q89: =IF(Refino!$L$15="","",G89*Refino!$L$15*(1-RetCraft)) | R89: 0 | S89: - | T89: =G89*Refino!$D$15 | U89: =T89*0.1125*FeeCraft/100 | V89: =IF(OR(Q89="",R89=""),"",Q89+R89+U89) | W89: =IF(O89="","",O89*(1-TaxaVenda)) | X89: =IF(OR(V89="",W89=""),"",W89-V89) | Y89: =IF(X89="","",X89/V89)
A90: Cavaleiro (Knight)|Armadura|T6.1 | B90: Cavaleiro (Knight) | C90: Armadura | D90: T6.1 | E90: 6 | F90: 1 | G90: 16 | O90: =IF(COUNT(H90:N90)=0,"",MAX(H90:N90)) | P90: =IF(O90="","",INDEX($H$3:$N$3,MATCH(O90,H90:N90,0))) | Q90: =IF(Refino!$L$16="","",G90*Refino!$L$16*(1-RetCraft)) | R90: 0 | S90: - | T90: =G90*Refino!$D$16 | U90: =T90*0.1125*FeeCraft/100 | V90: =IF(OR(Q90="",R90=""),"",Q90+R90+U90) | W90: =IF(O90="","",O90*(1-TaxaVenda)) | X90: =IF(OR(V90="",W90=""),"",W90-V90) | Y90: =IF(X90="","",X90/V90)
A91: Cavaleiro (Knight)|Armadura|T6.2 | B91: Cavaleiro (Knight) | C91: Armadura | D91: T6.2 | E91: 6 | F91: 2 | G91: 16 | O91: =IF(COUNT(H91:N91)=0,"",MAX(H91:N91)) | P91: =IF(O91="","",INDEX($H$3:$N$3,MATCH(O91,H91:N91,0))) | Q91: =IF(Refino!$L$17="","",G91*Refino!$L$17*(1-RetCraft)) | R91: 0 | S91: - | T91: =G91*Refino!$D$17 | U91: =T91*0.1125*FeeCraft/100 | V91: =IF(OR(Q91="",R91=""),"",Q91+R91+U91) | W91: =IF(O91="","",O91*(1-TaxaVenda)) | X91: =IF(OR(V91="",W91=""),"",W91-V91) | Y91: =IF(X91="","",X91/V91)
A92: Cavaleiro (Knight)|Armadura|T6.3 | B92: Cavaleiro (Knight) | C92: Armadura | D92: T6.3 | E92: 6 | F92: 3 | G92: 16 | O92: =IF(COUNT(H92:N92)=0,"",MAX(H92:N92)) | P92: =IF(O92="","",INDEX($H$3:$N$3,MATCH(O92,H92:N92,0))) | Q92: =IF(Refino!$L$18="","",G92*Refino!$L$18*(1-RetCraft)) | R92: 0 | S92: - | T92: =G92*Refino!$D$18 | U92: =T92*0.1125*FeeCraft/100 | V92: =IF(OR(Q92="",R92=""),"",Q92+R92+U92) | W92: =IF(O92="","",O92*(1-TaxaVenda)) | X92: =IF(OR(V92="",W92=""),"",W92-V92) | Y92: =IF(X92="","",X92/V92)
A93: Cavaleiro (Knight)|Armadura|T6.4 | B93: Cavaleiro (Knight) | C93: Armadura | D93: T6.4 | E93: 6 | F93: 4 | G93: 16 | O93: =IF(COUNT(H93:N93)=0,"",MAX(H93:N93)) | P93: =IF(O93="","",INDEX($H$3:$N$3,MATCH(O93,H93:N93,0))) | Q93: =IF(Refino!$L$19="","",G93*Refino!$L$19*(1-RetCraft)) | R93: 0 | S93: - | T93: =G93*Refino!$D$19 | U93: =T93*0.1125*FeeCraft/100 | V93: =IF(OR(Q93="",R93=""),"",Q93+R93+U93) | W93: =IF(O93="","",O93*(1-TaxaVenda)) | X93: =IF(OR(V93="",W93=""),"",W93-V93) | Y93: =IF(X93="","",X93/V93)
A94: Cavaleiro (Knight)|Armadura|T7.0 | B94: Cavaleiro (Knight) | C94: Armadura | D94: T7.0 | E94: 7 | F94: 0 | G94: 16 | O94: =IF(COUNT(H94:N94)=0,"",MAX(H94:N94)) | P94: =IF(O94="","",INDEX($H$3:$N$3,MATCH(O94,H94:N94,0))) | Q94: =IF(Refino!$L$20="","",G94*Refino!$L$20*(1-RetCraft)) | R94: 0 | S94: - | T94: =G94*Refino!$D$20 | U94: =T94*0.1125*FeeCraft/100 | V94: =IF(OR(Q94="",R94=""),"",Q94+R94+U94) | W94: =IF(O94="","",O94*(1-TaxaVenda)) | X94: =IF(OR(V94="",W94=""),"",W94-V94) | Y94: =IF(X94="","",X94/V94)
A95: Cavaleiro (Knight)|Armadura|T7.1 | B95: Cavaleiro (Knight) | C95: Armadura | D95: T7.1 | E95: 7 | F95: 1 | G95: 16 | O95: =IF(COUNT(H95:N95)=0,"",MAX(H95:N95)) | P95: =IF(O95="","",INDEX($H$3:$N$3,MATCH(O95,H95:N95,0))) | Q95: =IF(Refino!$L$21="","",G95*Refino!$L$21*(1-RetCraft)) | R95: 0 | S95: - | T95: =G95*Refino!$D$21 | U95: =T95*0.1125*FeeCraft/100 | V95: =IF(OR(Q95="",R95=""),"",Q95+R95+U95) | W95: =IF(O95="","",O95*(1-TaxaVenda)) | X95: =IF(OR(V95="",W95=""),"",W95-V95) | Y95: =IF(X95="","",X95/V95)
A96: Cavaleiro (Knight)|Armadura|T7.2 | B96: Cavaleiro (Knight) | C96: Armadura | D96: T7.2 | E96: 7 | F96: 2 | G96: 16 | O96: =IF(COUNT(H96:N96)=0,"",MAX(H96:N96)) | P96: =IF(O96="","",INDEX($H$3:$N$3,MATCH(O96,H96:N96,0))) | Q96: =IF(Refino!$L$22="","",G96*Refino!$L$22*(1-RetCraft)) | R96: 0 | S96: - | T96: =G96*Refino!$D$22 | U96: =T96*0.1125*FeeCraft/100 | V96: =IF(OR(Q96="",R96=""),"",Q96+R96+U96) | W96: =IF(O96="","",O96*(1-TaxaVenda)) | X96: =IF(OR(V96="",W96=""),"",W96-V96) | Y96: =IF(X96="","",X96/V96)
A97: Cavaleiro (Knight)|Armadura|T7.3 | B97: Cavaleiro (Knight) | C97: Armadura | D97: T7.3 | E97: 7 | F97: 3 | G97: 16 | O97: =IF(COUNT(H97:N97)=0,"",MAX(H97:N97)) | P97: =IF(O97="","",INDEX($H$3:$N$3,MATCH(O97,H97:N97,0))) | Q97: =IF(Refino!$L$23="","",G97*Refino!$L$23*(1-RetCraft)) | R97: 0 | S97: - | T97: =G97*Refino!$D$23 | U97: =T97*0.1125*FeeCraft/100 | V97: =IF(OR(Q97="",R97=""),"",Q97+R97+U97) | W97: =IF(O97="","",O97*(1-TaxaVenda)) | X97: =IF(OR(V97="",W97=""),"",W97-V97) | Y97: =IF(X97="","",X97/V97)
A98: Cavaleiro (Knight)|Armadura|T7.4 | B98: Cavaleiro (Knight) | C98: Armadura | D98: T7.4 | E98: 7 | F98: 4 | G98: 16 | O98: =IF(COUNT(H98:N98)=0,"",MAX(H98:N98)) | P98: =IF(O98="","",INDEX($H$3:$N$3,MATCH(O98,H98:N98,0))) | Q98: =IF(Refino!$L$24="","",G98*Refino!$L$24*(1-RetCraft)) | R98: 0 | S98: - | T98: =G98*Refino!$D$24 | U98: =T98*0.1125*FeeCraft/100 | V98: =IF(OR(Q98="",R98=""),"",Q98+R98+U98) | W98: =IF(O98="","",O98*(1-TaxaVenda)) | X98: =IF(OR(V98="",W98=""),"",W98-V98) | Y98: =IF(X98="","",X98/V98)
A99: Cavaleiro (Knight)|Armadura|T8.0 | B99: Cavaleiro (Knight) | C99: Armadura | D99: T8.0 | E99: 8 | F99: 0 | G99: 16 | O99: =IF(COUNT(H99:N99)=0,"",MAX(H99:N99)) | P99: =IF(O99="","",INDEX($H$3:$N$3,MATCH(O99,H99:N99,0))) | Q99: =IF(Refino!$L$25="","",G99*Refino!$L$25*(1-RetCraft)) | R99: 0 | S99: - | T99: =G99*Refino!$D$25 | U99: =T99*0.1125*FeeCraft/100 | V99: =IF(OR(Q99="",R99=""),"",Q99+R99+U99) | W99: =IF(O99="","",O99*(1-TaxaVenda)) | X99: =IF(OR(V99="",W99=""),"",W99-V99) | Y99: =IF(X99="","",X99/V99)
A100: Cavaleiro (Knight)|Armadura|T8.1 | B100: Cavaleiro (Knight) | C100: Armadura | D100: T8.1 | E100: 8 | F100: 1 | G100: 16 | O100: =IF(COUNT(H100:N100)=0,"",MAX(H100:N100)) | P100: =IF(O100="","",INDEX($H$3:$N$3,MATCH(O100,H100:N100,0))) | Q100: =IF(Refino!$L$26="","",G100*Refino!$L$26*(1-RetCraft)) | R100: 0 | S100: - | T100: =G100*Refino!$D$26 | U100: =T100*0.1125*FeeCraft/100 | V100: =IF(OR(Q100="",R100=""),"",Q100+R100+U100) | W100: =IF(O100="","",O100*(1-TaxaVenda)) | X100: =IF(OR(V100="",W100=""),"",W100-V100) | Y100: =IF(X100="","",X100/V100)
...

Sheet Refino
A1: Refino de barras: refinar x comprar (custo unitário real)
A2: Barra | B2: Tier | C2: Encant. | D2: Valor do item | E2: Qtd minério | F2: Barra inferior | G2: Preço minério (c/ taxa) | H2: Custo ao REFINAR | I2: Preço barra pronta (c/ taxa) | J2: Cidade (barra pronta) | K2: Origem | L2: CUSTO EFETIVO da barra | M2: Decisão | N2: Demanda direta (Craft) | O2: Demanda por refino superior | P2: Demanda total | Q2: Barras a COMPRAR | R2: Barras a REFINAR | S2: Minério necessário | T2: Custo compra barras | U2: Custo minério | V2: Cidade minério
A3: T2.0 | B3: 2 | C3: 0 | D3: =2^B3*2^C3 | E3: 1 | F3: - | G3: =IF(Minerio!G3="","",Minerio!G3*(1+TaxaCompra)) | H3: =IF(G3="","",E3*G3*(1-RetRefino)+D3*0.1125*FeeRefino/100) | I3: =IF(Barras!G3="","",Barras!G3*(1+TaxaCompra)) | J3: =IF(Barras!H3="","",Barras!H3) | K3: Automático | L3: =IF(K3="Comprar",I3,IF(K3="Refinar",H3,IF(AND(H3="",I3=""),"",IF(H3="",I3,IF(I3="",H3,MIN(H3,I3)))))) | M3: =IF(L3="","",IF(K3="Comprar","Comprar",IF(K3="Refinar","Refinar",IF(H3="","Comprar",IF(I3="","Refinar",IF(H3<=I3,"Refinar","Comprar")))))) | N3: =SUMIF(Craft!$C$6:$C$35,$A3,Craft!$S$6:$S$35) | O3: =IF(M4="Refinar",P4*(1-RetRefino),0) | P3: =N3+O3 | Q3: =IF(M3="Comprar",P3,0) | R3: =IF(M3="Refinar",P3,0) | S3: =R3*E3*(1-RetRefino) | T3: =IF(AND(Q3>0,ISNUMBER(I3)),Q3*I3,0) | U3: =IF(AND(S3>0,ISNUMBER(G3)),S3*G3,0) | V3: =IF(Minerio!H3="","",Minerio!H3)
A4: T3.0 | B4: 3 | C4: 0 | D4: =2^B4*2^C4 | E4: 2 | F4: T2.0 | G4: =IF(Minerio!G4="","",Minerio!G4*(1+TaxaCompra)) | H4: =IF(OR(G4="",L3=""),"",(E4*G4+L3)*(1-RetRefino)+D4*0.1125*FeeRefino/100) | I4: =IF(Barras!G4="","",Barras!G4*(1+TaxaCompra)) | J4: =IF(Barras!H4="","",Barras!H4) | K4: Automático | L4: =IF(K4="Comprar",I4,IF(K4="Refinar",H4,IF(AND(H4="",I4=""),"",IF(H4="",I4,IF(I4="",H4,MIN(H4,I4)))))) | M4: =IF(L4="","",IF(K4="Comprar","Comprar",IF(K4="Refinar","Refinar",IF(H4="","Comprar",IF(I4="","Refinar",IF(H4<=I4,"Refinar","Comprar")))))) | N4: =SUMIF(Craft!$C$6:$C$35,$A4,Craft!$S$6:$S$35) | O4: =IF(M5="Refinar",P5*(1-RetRefino),0)+IF(M6="Refinar",P6*(1-RetRefino),0)+IF(M7="Refinar",P7*(1-RetRefino),0)+IF(M8="Refinar",P8*(1-RetRefino),0)+IF(M9="Refinar",P9*(1-RetRefino),0) | P4: =N4+O4 | Q4: =IF(M4="Comprar",P4,0) | R4: =IF(M4="Refinar",P4,0) | S4: =R4*E4*(1-RetRefino) | T4: =IF(AND(Q4>0,ISNUMBER(I4)),Q4*I4,0) | U4: =IF(AND(S4>0,ISNUMBER(G4)),S4*G4,0) | V4: =IF(Minerio!H4="","",Minerio!H4)
A5: T4.0 | B5: 4 | C5: 0 | D5: =2^B5*2^C5 | E5: 2 | F5: T3.0 | G5: =IF(Minerio!G5="","",Minerio!G5*(1+TaxaCompra)) | H5: =IF(OR(G5="",L4=""),"",(E5*G5+L4)*(1-RetRefino)+D5*0.1125*FeeRefino/100) | I5: =IF(Barras!G5="","",Barras!G5*(1+TaxaCompra)) | J5: =IF(Barras!H5="","",Barras!H5) | K5: Automático | L5: =IF(K5="Comprar",I5,IF(K5="Refinar",H5,IF(AND(H5="",I5=""),"",IF(H5="",I5,IF(I5="",H5,MIN(H5,I5)))))) | M5: =IF(L5="","",IF(K5="Comprar","Comprar",IF(K5="Refinar","Refinar",IF(H5="","Comprar",IF(I5="","Refinar",IF(H5<=I5,"Refinar","Comprar")))))) | N5: =SUMIF(Craft!$C$6:$C$35,$A5,Craft!$S$6:$S$35) | O5: =IF(M10="Refinar",P10*(1-RetRefino),0) | P5: =N5+O5 | Q5: =IF(M5="Comprar",P5,0) | R5: =IF(M5="Refinar",P5,0) | S5: =R5*E5*(1-RetRefino) | T5: =IF(AND(Q5>0,ISNUMBER(I5)),Q5*I5,0) | U5: =IF(AND(S5>0,ISNUMBER(G5)),S5*G5,0) | V5: =IF(Minerio!H5="","",Minerio!H5)
A6: T4.1 | B6: 4 | C6: 1 | D6: =2^B6*2^C6 | E6: 2 | F6: T3.0 | G6: =IF(Minerio!G6="","",Minerio!G6*(1+TaxaCompra)) | H6: =IF(OR(G6="",L4=""),"",(E6*G6+L4)*(1-RetRefino)+D6*0.1125*FeeRefino/100) | I6: =IF(Barras!G6="","",Barras!G6*(1+TaxaCompra)) | J6: =IF(Barras!H6="","",Barras!H6) | K6: Automático | L6: =IF(K6="Comprar",I6,IF(K6="Refinar",H6,IF(AND(H6="",I6=""),"",IF(H6="",I6,IF(I6="",H6,MIN(H6,I6)))))) | M6: =IF(L6="","",IF(K6="Comprar","Comprar",IF(K6="Refinar","Refinar",IF(H6="","Comprar",IF(I6="","Refinar",IF(H6<=I6,"Refinar","Comprar")))))) | N6: =SUMIF(Craft!$C$6:$C$35,$A6,Craft!$S$6:$S$35) | O6: =IF(M11="Refinar",P11*(1-RetRefino),0) | P6: =N6+O6 | Q6: =IF(M6="Comprar",P6,0) | R6: =IF(M6="Refinar",P6,0) | S6: =R6*E6*(1-RetRefino) | T6: =IF(AND(Q6>0,ISNUMBER(I6)),Q6*I6,0) | U6: =IF(AND(S6>0,ISNUMBER(G6)),S6*G6,0) | V6: =IF(Minerio!H6="","",Minerio!H6)
A7: T4.2 | B7: 4 | C7: 2 | D7: =2^B7*2^C7 | E7: 2 | F7: T3.0 | G7: =IF(Minerio!G7="","",Minerio!G7*(1+TaxaCompra)) | H7: =IF(OR(G7="",L4=""),"",(E7*G7+L4)*(1-RetRefino)+D7*0.1125*FeeRefino/100) | I7: =IF(Barras!G7="","",Barras!G7*(1+TaxaCompra)) | J7: =IF(Barras!H7="","",Barras!H7) | K7: Automático | L7: =IF(K7="Comprar",I7,IF(K7="Refinar",H7,IF(AND(H7="",I7=""),"",IF(H7="",I7,IF(I7="",H7,MIN(H7,I7)))))) | M7: =IF(L7="","",IF(K7="Comprar","Comprar",IF(K7="Refinar","Refinar",IF(H7="","Comprar",IF(I7="","Refinar",IF(H7<=I7,"Refinar","Comprar")))))) | N7: =SUMIF(Craft!$C$6:$C$35,$A7,Craft!$S$6:$S$35) | O7: =IF(M12="Refinar",P12*(1-RetRefino),0) | P7: =N7+O7 | Q7: =IF(M7="Comprar",P7,0) | R7: =IF(M7="Refinar",P7,0) | S7: =R7*E7*(1-RetRefino) | T7: =IF(AND(Q7>0,ISNUMBER(I7)),Q7*I7,0) | U7: =IF(AND(S7>0,ISNUMBER(G7)),S7*G7,0) | V7: =IF(Minerio!H7="","",Minerio!H7)
A8: T4.3 | B8: 4 | C8: 3 | D8: =2^B8*2^C8 | E8: 2 | F8: T3.0 | G8: =IF(Minerio!G8="","",Minerio!G8*(1+TaxaCompra)) | H8: =IF(OR(G8="",L4=""),"",(E8*G8+L4)*(1-RetRefino)+D8*0.1125*FeeRefino/100) | I8: =IF(Barras!G8="","",Barras!G8*(1+TaxaCompra)) | J8: =IF(Barras!H8="","",Barras!H8) | K8: Automático | L8: =IF(K8="Comprar",I8,IF(K8="Refinar",H8,IF(AND(H8="",I8=""),"",IF(H8="",I8,IF(I8="",H8,MIN(H8,I8)))))) | M8: =IF(L8="","",IF(K8="Comprar","Comprar",IF(K8="Refinar","Refinar",IF(H8="","Comprar",IF(I8="","Refinar",IF(H8<=I8,"Refinar","Comprar")))))) | N8: =SUMIF(Craft!$C$6:$C$35,$A8,Craft!$S$6:$S$35) | O8: =IF(M13="Refinar",P13*(1-RetRefino),0) | P8: =N8+O8 | Q8: =IF(M8="Comprar",P8,0) | R8: =IF(M8="Refinar",P8,0) | S8: =R8*E8*(1-RetRefino) | T8: =IF(AND(Q8>0,ISNUMBER(I8)),Q8*I8,0) | U8: =IF(AND(S8>0,ISNUMBER(G8)),S8*G8,0) | V8: =IF(Minerio!H8="","",Minerio!H8)
A9: T4.4 | B9: 4 | C9: 4 | D9: =2^B9*2^C9 | E9: 2 | F9: T3.0 | G9: =IF(Minerio!G9="","",Minerio!G9*(1+TaxaCompra)) | H9: =IF(OR(G9="",L4=""),"",(E9*G9+L4)*(1-RetRefino)+D9*0.1125*FeeRefino/100) | I9: =IF(Barras!G9="","",Barras!G9*(1+TaxaCompra)) | J9: =IF(Barras!H9="","",Barras!H9) | K9: Automático | L9: =IF(K9="Comprar",I9,IF(K9="Refinar",H9,IF(AND(H9="",I9=""),"",IF(H9="",I9,IF(I9="",H9,MIN(H9,I9)))))) | M9: =IF(L9="","",IF(K9="Comprar","Comprar",IF(K9="Refinar","Refinar",IF(H9="","Comprar",IF(I9="","Refinar",IF(H9<=I9,"Refinar","Comprar")))))) | N9: =SUMIF(Craft!$C$6:$C$35,$A9,Craft!$S$6:$S$35) | O9: =IF(M14="Refinar",P14*(1-RetRefino),0) | P9: =N9+O9 | Q9: =IF(M9="Comprar",P9,0) | R9: =IF(M9="Refinar",P9,0) | S9: =R9*E9*(1-RetRefino) | T9: =IF(AND(Q9>0,ISNUMBER(I9)),Q9*I9,0) | U9: =IF(AND(S9>0,ISNUMBER(G9)),S9*G9,0) | V9: =IF(Minerio!H9="","",Minerio!H9)
A10: T5.0 | B10: 5 | C10: 0 | D10: =2^B10*2^C10 | E10: 3 | F10: T4.0 | G10: =IF(Minerio!G10="","",Minerio!G10*(1+TaxaCompra)) | H10: =IF(OR(G10="",L5=""),"",(E10*G10+L5)*(1-RetRefino)+D10*0.1125*FeeRefino/100) | I10: =IF(Barras!G10="","",Barras!G10*(1+TaxaCompra)) | J10: =IF(Barras!H10="","",Barras!H10) | K10: Automático | L10: =IF(K10="Comprar",I10,IF(K10="Refinar",H10,IF(AND(H10="",I10=""),"",IF(H10="",I10,IF(I10="",H10,MIN(H10,I10)))))) | M10: =IF(L10="","",IF(K10="Comprar","Comprar",IF(K10="Refinar","Refinar",IF(H10="","Comprar",IF(I10="","Refinar",IF(H10<=I10,"Refinar","Comprar")))))) | N10: =SUMIF(Craft!$C$6:$C$35,$A10,Craft!$S$6:$S$35) | O10: =IF(M15="Refinar",P15*(1-RetRefino),0) | P10: =N10+O10 | Q10: =IF(M10="Comprar",P10,0) | R10: =IF(M10="Refinar",P10,0) | S10: =R10*E10*(1-RetRefino) | T10: =IF(AND(Q10>0,ISNUMBER(I10)),Q10*I10,0) | U10: =IF(AND(S10>0,ISNUMBER(G10)),S10*G10,0) | V10: =IF(Minerio!H10="","",Minerio!H10)
A11: T5.1 | B11: 5 | C11: 1 | D11: =2^B11*2^C11 | E11: 3 | F11: T4.1 | G11: =IF(Minerio!G11="","",Minerio!G11*(1+TaxaCompra)) | H11: =IF(OR(G11="",L6=""),"",(E11*G11+L6)*(1-RetRefino)+D11*0.1125*FeeRefino/100) | I11: =IF(Barras!G11="","",Barras!G11*(1+TaxaCompra)) | J11: =IF(Barras!H11="","",Barras!H11) | K11: Automático | L11: =IF(K11="Comprar",I11,IF(K11="Refinar",H11,IF(AND(H11="",I11=""),"",IF(H11="",I11,IF(I11="",H11,MIN(H11,I11)))))) | M11: =IF(L11="","",IF(K11="Comprar","Comprar",IF(K11="Refinar","Refinar",IF(H11="","Comprar",IF(I11="","Refinar",IF(H11<=I11,"Refinar","Comprar")))))) | N11: =SUMIF(Craft!$C$6:$C$35,$A11,Craft!$S$6:$S$35) | O11: =IF(M16="Refinar",P16*(1-RetRefino),0) | P11: =N11+O11 | Q11: =IF(M11="Comprar",P11,0) | R11: =IF(M11="Refinar",P11,0) | S11: =R11*E11*(1-RetRefino) | T11: =IF(AND(Q11>0,ISNUMBER(I11)),Q11*I11,0) | U11: =IF(AND(S11>0,ISNUMBER(G11)),S11*G11,0) | V11: =IF(Minerio!H11="","",Minerio!H11)
A12: T5.2 | B12: 5 | C12: 2 | D12: =2^B12*2^C12 | E12: 3 | F12: T4.2 | G12: =IF(Minerio!G12="","",Minerio!G12*(1+TaxaCompra)) | H12: =IF(OR(G12="",L7=""),"",(E12*G12+L7)*(1-RetRefino)+D12*0.1125*FeeRefino/100) | I12: =IF(Barras!G12="","",Barras!G12*(1+TaxaCompra)) | J12: =IF(Barras!H12="","",Barras!H12) | K12: Automático | L12: =IF(K12="Comprar",I12,IF(K12="Refinar",H12,IF(AND(H12="",I12=""),"",IF(H12="",I12,IF(I12="",H12,MIN(H12,I12)))))) | M12: =IF(L12="","",IF(K12="Comprar","Comprar",IF(K12="Refinar","Refinar",IF(H12="","Comprar",IF(I12="","Refinar",IF(H12<=I12,"Refinar","Comprar")))))) | N12: =SUMIF(Craft!$C$6:$C$35,$A12,Craft!$S$6:$S$35) | O12: =IF(M17="Refinar",P17*(1-RetRefino),0) | P12: =N12+O12 | Q12: =IF(M12="Comprar",P12,0) | R12: =IF(M12="Refinar",P12,0) | S12: =R12*E12*(1-RetRefino) | T12: =IF(AND(Q12>0,ISNUMBER(I12)),Q12*I12,0) | U12: =IF(AND(S12>0,ISNUMBER(G12)),S12*G12,0) | V12: =IF(Minerio!H12="","",Minerio!H12)
A13: T5.3 | B13: 5 | C13: 3 | D13: =2^B13*2^C13 | E13: 3 | F13: T4.3 | G13: =IF(Minerio!G13="","",Minerio!G13*(1+TaxaCompra)) | H13: =IF(OR(G13="",L8=""),"",(E13*G13+L8)*(1-RetRefino)+D13*0.1125*FeeRefino/100) | I13: =IF(Barras!G13="","",Barras!G13*(1+TaxaCompra)) | J13: =IF(Barras!H13="","",Barras!H13) | K13: Automático | L13: =IF(K13="Comprar",I13,IF(K13="Refinar",H13,IF(AND(H13="",I13=""),"",IF(H13="",I13,IF(I13="",H13,MIN(H13,I13)))))) | M13: =IF(L13="","",IF(K13="Comprar","Comprar",IF(K13="Refinar","Refinar",IF(H13="","Comprar",IF(I13="","Refinar",IF(H13<=I13,"Refinar","Comprar")))))) | N13: =SUMIF(Craft!$C$6:$C$35,$A13,Craft!$S$6:$S$35) | O13: =IF(M18="Refinar",P18*(1-RetRefino),0) | P13: =N13+O13 | Q13: =IF(M13="Comprar",P13,0) | R13: =IF(M13="Refinar",P13,0) | S13: =R13*E13*(1-RetRefino) | T13: =IF(AND(Q13>0,ISNUMBER(I13)),Q13*I13,0) | U13: =IF(AND(S13>0,ISNUMBER(G13)),S13*G13,0) | V13: =IF(Minerio!H13="","",Minerio!H13)
A14: T5.4 | B14: 5 | C14: 4 | D14: =2^B14*2^C14 | E14: 3 | F14: T4.4 | G14: =IF(Minerio!G14="","",Minerio!G14*(1+TaxaCompra)) | H14: =IF(OR(G14="",L9=""),"",(E14*G14+L9)*(1-RetRefino)+D14*0.1125*FeeRefino/100) | I14: =IF(Barras!G14="","",Barras!G14*(1+TaxaCompra)) | J14: =IF(Barras!H14="","",Barras!H14) | K14: Automático | L14: =IF(K14="Comprar",I14,IF(K14="Refinar",H14,IF(AND(H14="",I14=""),"",IF(H14="",I14,IF(I14="",H14,MIN(H14,I14)))))) | M14: =IF(L14="","",IF(K14="Comprar","Comprar",IF(K14="Refinar","Refinar",IF(H14="","Comprar",IF(I14="","Refinar",IF(H14<=I14,"Refinar","Comprar")))))) | N14: =SUMIF(Craft!$C$6:$C$35,$A14,Craft!$S$6:$S$35) | O14: =IF(M19="Refinar",P19*(1-RetRefino),0) | P14: =N14+O14 | Q14: =IF(M14="Comprar",P14,0) | R14: =IF(M14="Refinar",P14,0) | S14: =R14*E14*(1-RetRefino) | T14: =IF(AND(Q14>0,ISNUMBER(I14)),Q14*I14,0) | U14: =IF(AND(S14>0,ISNUMBER(G14)),S14*G14,0) | V14: =IF(Minerio!H14="","",Minerio!H14)
A15: T6.0 | B15: 6 | C15: 0 | D15: =2^B15*2^C15 | E15: 4 | F15: T5.0 | G15: =IF(Minerio!G15="","",Minerio!G15*(1+TaxaCompra)) | H15: =IF(OR(G15="",L10=""),"",(E15*G15+L10)*(1-RetRefino)+D15*0.1125*FeeRefino/100) | I15: =IF(Barras!G15="","",Barras!G15*(1+TaxaCompra)) | J15: =IF(Barras!H15="","",Barras!H15) | K15: Automático | L15: =IF(K15="Comprar",I15,IF(K15="Refinar",H15,IF(AND(H15="",I15=""),"",IF(H15="",I15,IF(I15="",H15,MIN(H15,I15)))))) | M15: =IF(L15="","",IF(K15="Comprar","Comprar",IF(K15="Refinar","Refinar",IF(H15="","Comprar",IF(I15="","Refinar",IF(H15<=I15,"Refinar","Comprar")))))) | N15: =SUMIF(Craft!$C$6:$C$35,$A15,Craft!$S$6:$S$35) | O15: =IF(M20="Refinar",P20*(1-RetRefino),0) | P15: =N15+O15 | Q15: =IF(M15="Comprar",P15,0) | R15: =IF(M15="Refinar",P15,0) | S15: =R15*E15*(1-RetRefino) | T15: =IF(AND(Q15>0,ISNUMBER(I15)),Q15*I15,0) | U15: =IF(AND(S15>0,ISNUMBER(G15)),S15*G15,0) | V15: =IF(Minerio!H15="","",Minerio!H15)
A16: T6.1 | B16: 6 | C16: 1 | D16: =2^B16*2^C16 | E16: 4 | F16: T5.1 | G16: =IF(Minerio!G16="","",Minerio!G16*(1+TaxaCompra)) | H16: =IF(OR(G16="",L11=""),"",(E16*G16+L11)*(1-RetRefino)+D16*0.1125*FeeRefino/100) | I16: =IF(Barras!G16="","",Barras!G16*(1+TaxaCompra)) | J16: =IF(Barras!H16="","",Barras!H16) | K16: Automático | L16: =IF(K16="Comprar",I16,IF(K16="Refinar",H16,IF(AND(H16="",I16=""),"",IF(H16="",I16,IF(I16="",H16,MIN(H16,I16)))))) | M16: =IF(L16="","",IF(K16="Comprar","Comprar",IF(K16="Refinar","Refinar",IF(H16="","Comprar",IF(I16="","Refinar",IF(H16<=I16,"Refinar","Comprar")))))) | N16: =SUMIF(Craft!$C$6:$C$35,$A16,Craft!$S$6:$S$35) | O16: =IF(M21="Refinar",P21*(1-RetRefino),0) | P16: =N16+O16 | Q16: =IF(M16="Comprar",P16,0) | R16: =IF(M16="Refinar",P16,0) | S16: =R16*E16*(1-RetRefino) | T16: =IF(AND(Q16>0,ISNUMBER(I16)),Q16*I16,0) | U16: =IF(AND(S16>0,ISNUMBER(G16)),S16*G16,0) | V16: =IF(Minerio!H16="","",Minerio!H16)
A17: T6.2 | B17: 6 | C17: 2 | D17: =2^B17*2^C17 | E17: 4 | F17: T5.2 | G17: =IF(Minerio!G17="","",Minerio!G17*(1+TaxaCompra)) | H17: =IF(OR(G17="",L12=""),"",(E17*G17+L12)*(1-RetRefino)+D17*0.1125*FeeRefino/100) | I17: =IF(Barras!G17="","",Barras!G17*(1+TaxaCompra)) | J17: =IF(Barras!H17="","",Barras!H17) | K17: Automático | L17: =IF(K17="Comprar",I17,IF(K17="Refinar",H17,IF(AND(H17="",I17=""),"",IF(H17="",I17,IF(I17="",H17,MIN(H17,I17)))))) | M17: =IF(L17="","",IF(K17="Comprar","Comprar",IF(K17="Refinar","Refinar",IF(H17="","Comprar",IF(I17="","Refinar",IF(H17<=I17,"Refinar","Comprar")))))) | N17: =SUMIF(Craft!$C$6:$C$35,$A17,Craft!$S$6:$S$35) | O17: =IF(M22="Refinar",P22*(1-RetRefino),0) | P17: =N17+O17 | Q17: =IF(M17="Comprar",P17,0) | R17: =IF(M17="Refinar",P17,0) | S17: =R17*E17*(1-RetRefino) | T17: =IF(AND(Q17>0,ISNUMBER(I17)),Q17*I17,0) | U17: =IF(AND(S17>0,ISNUMBER(G17)),S17*G17,0) | V17: =IF(Minerio!H17="","",Minerio!H17)
A18: T6.3 | B18: 6 | C18: 3 | D18: =2^B18*2^C18 | E18: 4 | F18: T5.3 | G18: =IF(Minerio!G18="","",Minerio!G18*(1+TaxaCompra)) | H18: =IF(OR(G18="",L13=""),"",(E18*G18+L13)*(1-RetRefino)+D18*0.1125*FeeRefino/100) | I18: =IF(Barras!G18="","",Barras!G18*(1+TaxaCompra)) | J18: =IF(Barras!H18="","",Barras!H18) | K18: Automático | L18: =IF(K18="Comprar",I18,IF(K18="Refinar",H18,IF(AND(H18="",I18=""),"",IF(H18="",I18,IF(I18="",H18,MIN(H18,I18)))))) | M18: =IF(L18="","",IF(K18="Comprar","Comprar",IF(K18="Refinar","Refinar",IF(H18="","Comprar",IF(I18="","Refinar",IF(H18<=I18,"Refinar","Comprar")))))) | N18: =SUMIF(Craft!$C$6:$C$35,$A18,Craft!$S$6:$S$35) | O18: =IF(M23="Refinar",P23*(1-RetRefino),0) | P18: =N18+O18 | Q18: =IF(M18="Comprar",P18,0) | R18: =IF(M18="Refinar",P18,0) | S18: =R18*E18*(1-RetRefino) | T18: =IF(AND(Q18>0,ISNUMBER(I18)),Q18*I18,0) | U18: =IF(AND(S18>0,ISNUMBER(G18)),S18*G18,0) | V18: =IF(Minerio!H18="","",Minerio!H18)
A19: T6.4 | B19: 6 | C19: 4 | D19: =2^B19*2^C19 | E19: 4 | F19: T5.4 | G19: =IF(Minerio!G19="","",Minerio!G19*(1+TaxaCompra)) | H19: =IF(OR(G19="",L14=""),"",(E19*G19+L14)*(1-RetRefino)+D19*0.1125*FeeRefino/100) | I19: =IF(Barras!G19="","",Barras!G19*(1+TaxaCompra)) | J19: =IF(Barras!H19="","",Barras!H19) | K19: Automático | L19: =IF(K19="Comprar",I19,IF(K19="Refinar",H19,IF(AND(H19="",I19=""),"",IF(H19="",I19,IF(I19="",H19,MIN(H19,I19)))))) | M19: =IF(L19="","",IF(K19="Comprar","Comprar",IF(K19="Refinar","Refinar",IF(H19="","Comprar",IF(I19="","Refinar",IF(H19<=I19,"Refinar","Comprar")))))) | N19: =SUMIF(Craft!$C$6:$C$35,$A19,Craft!$S$6:$S$35) | O19: =IF(M24="Refinar",P24*(1-RetRefino),0) | P19: =N19+O19 | Q19: =IF(M19="Comprar",P19,0) | R19: =IF(M19="Refinar",P19,0) | S19: =R19*E19*(1-RetRefino) | T19: =IF(AND(Q19>0,ISNUMBER(I19)),Q19*I19,0) | U19: =IF(AND(S19>0,ISNUMBER(G19)),S19*G19,0) | V19: =IF(Minerio!H19="","",Minerio!H19)
A20: T7.0 | B20: 7 | C20: 0 | D20: =2^B20*2^C20 | E20: 5 | F20: T6.0 | G20: =IF(Minerio!G20="","",Minerio!G20*(1+TaxaCompra)) | H20: =IF(OR(G20="",L15=""),"",(E20*G20+L15)*(1-RetRefino)+D20*0.1125*FeeRefino/100) | I20: =IF(Barras!G20="","",Barras!G20*(1+TaxaCompra)) | J20: =IF(Barras!H20="","",Barras!H20) | K20: Automático | L20: =IF(K20="Comprar",I20,IF(K20="Refinar",H20,IF(AND(H20="",I20=""),"",IF(H20="",I20,IF(I20="",H20,MIN(H20,I20)))))) | M20: =IF(L20="","",IF(K20="Comprar","Comprar",IF(K20="Refinar","Refinar",IF(H20="","Comprar",IF(I20="","Refinar",IF(H20<=I20,"Refinar","Comprar")))))) | N20: =SUMIF(Craft!$C$6:$C$35,$A20,Craft!$S$6:$S$35) | O20: =IF(M25="Refinar",P25*(1-RetRefino),0) | P20: =N20+O20 | Q20: =IF(M20="Comprar",P20,0) | R20: =IF(M20="Refinar",P20,0) | S20: =R20*E20*(1-RetRefino) | T20: =IF(AND(Q20>0,ISNUMBER(I20)),Q20*I20,0) | U20: =IF(AND(S20>0,ISNUMBER(G20)),S20*G20,0) | V20: =IF(Minerio!H20="","",Minerio!H20)
... A24: T7.4 | B24: 7 | C24: 4 | D24: =2^B24*2^C24 | E24: 5 | F24: T6.4 | G24: =IF(Minerio!G24="","",Minerio!G24*(1+TaxaCompra)) | H24: =IF(OR(G24="",L19=""),"",(E24*G24+L19)*(1-RetRefino)+D24*0.1125*FeeRefino/100) | I24: =IF(Barras!G24="","",Barras!G24*(1+TaxaCompra)) | J24: =IF(Barras!H24="","",Barras!H24) | K24: Automático | L24: =IF(K24="Comprar",I24,IF(K24="Refinar",H24,IF(AND(H24="",I24=""),"",IF(H24="",I24,IF(I24="",H24,MIN(H24,I24)))))) | M24: =IF(L24="","",IF(K24="Comprar","Comprar",IF(K24="Refinar","Refinar",IF(H24="","Comprar",IF(I24="","Refinar",IF(H24<=I24,"Refinar","Comprar")))))) | N24: =SUMIF(Craft!$C$6:$C$35,$A24,Craft!$S$6:$S$35) | O24: =IF(M29="Refinar",P29*(1-RetRefino),0) | P24: =N24+O24 | Q24: =IF(M24="Comprar",P24,0) | R24: =IF(M24="Refinar",P24,0) | S24: =R24*E24*(1-RetRefino) | T24: =IF(AND(Q24>0,ISNUMBER(I24)),Q24*I24,0) | U24: =IF(AND(S24>0,ISNUMBER(G24)),S24*G24,0) | V24: =IF(Minerio!H24="","",Minerio!H24)
A25: T8.0 | B25: 8 | C25: 0 | D25: =2^B25*2^C25 | E25: 5 | F25: T7.0 | G25: =IF(Minerio!G25="","",Minerio!G25*(1+TaxaCompra)) | H25: =IF(OR(G25="",L20=""),"",(E25*G25+L20)*(1-RetRefino)+D25*0.1125*FeeRefino/100) | I25: =IF(Barras!G25="","",Barras!G25*(1+TaxaCompra)) | J25: =IF(Barras!H25="","",Barras!H25) | K25: Automático | L25: =IF(K25="Comprar",I25,IF(K25="Refinar",H25,IF(AND(H25="",I25=""),"",IF(H25="",I25,IF(I25="",H25,MIN(H25,I25)))))) | M25: =IF(L25="","",IF(K25="Comprar","Comprar",IF(K25="Refinar","Refinar",IF(H25="","Comprar",IF(I25="","Refinar",IF(H25<=I25,"Refinar","Comprar")))))) | N25: =SUMIF(Craft!$C$6:$C$35,$A25,Craft!$S$6:$S$35) | O25: 0 | P25: =N25+O25 | Q25: =IF(M25="Comprar",P25,0) | R25: =IF(M25="Refinar",P25,0) | S25: =R25*E25*(1-RetRefino) | T25: =IF(AND(Q25>0,ISNUMBER(I25)),Q25*I25,0) | U25: =IF(AND(S25>0,ISNUMBER(G25)),S25*G25,0) | V25: =IF(Minerio!H25="","",Minerio!H25)
A26: T8.1 | B26: 8 | C26: 1 | D26: =2^B26*2^C26 | E26: 5 | F26: T7.1 | G26: =IF(Minerio!G26="","",Minerio!G26*(1+TaxaCompra)) | H26: =IF(OR(G26="",L21=""),"",(E26*G26+L21)*(1-RetRefino)+D26*0.1125*FeeRefino/100) | I26: =IF(Barras!G26="","",Barras!G26*(1+TaxaCompra)) | J26: =IF(Barras!H26="","",Barras!H26) | K26: Automático | L26: =IF(K26="Comprar",I26,IF(K26="Refinar",H26,IF(AND(H26="",I26=""),"",IF(H26="",I26,IF(I26="",H26,MIN(H26,I26)))))) | M26: =IF(L26="","",IF(K26="Comprar","Comprar",IF(K26="Refinar","Refinar",IF(H26="","Comprar",IF(I26="","Refinar",IF(H26<=I26,"Refinar","Comprar")))))) | N26: =SUMIF(Craft!$C$6:$C$35,$A26,Craft!$S$6:$S$35) | O26: 0 | P26: =N26+O26 | Q26: =IF(M26="Comprar",P26,0) | R26: =IF(M26="Refinar",P26,0) | S26: =R26*E26*(1-RetRefino) | T26: =IF(AND(Q26>0,ISNUMBER(I26)),Q26*I26,0) | U26: =IF(AND(S26>0,ISNUMBER(G26)),S26*G26,0) | V26: =IF(Minerio!H26="","",Minerio!H26)
A27: T8.2 | B27: 8 | C27: 2 | D27: =2^B27*2^C27 | E27: 5 | F27: T7.2 | G27: =IF(Minerio!G27="","",Minerio!G27*(1+TaxaCompra)) | H27: =IF(OR(G27="",L22=""),"",(E27*G27+L22)*(1-RetRefino)+D27*0.1125*FeeRefino/100) | I27: =IF(Barras!G27="","",Barras!G27*(1+TaxaCompra)) | J27: =IF(Barras!H27="","",Barras!H27) | K27: Automático | L27: =IF(K27="Comprar",I27,IF(K27="Refinar",H27,IF(AND(H27="",I27=""),"",IF(H27="",I27,IF(I27="",H27,MIN(H27,I27)))))) | M27: =IF(L27="","",IF(K27="Comprar","Comprar",IF(K27="Refinar","Refinar",IF(H27="","Comprar",IF(I27="","Refinar",IF(H27<=I27,"Refinar","Comprar")))))) | N27: =SUMIF(Craft!$C$6:$C$35,$A27,Craft!$S$6:$S$35) | O27: 0 | P27: =N27+O27 | Q27: =IF(M27="Comprar",P27,0) | R27: =IF(M27="Refinar",P27,0) | S27: =R27*E27*(1-RetRefino) | T27: =IF(AND(Q27>0,ISNUMBER(I27)),Q27*I27,0) | U27: =IF(AND(S27>0,ISNUMBER(G27)),S27*G27,0) | V27: =IF(Minerio!H27="","",Minerio!H27)
A28: T8.3 | B28: 8 | C28: 3 | D28: =2^B28*2^C28 | E28: 5 | F28: T7.3 | G28: =IF(Minerio!G28="","",Minerio!G28*(1+TaxaCompra)) | H28: =IF(OR(G28="",L23=""),"",(E28*G28+L23)*(1-RetRefino)+D28*0.1125*FeeRefino/100) | I28: =IF(Barras!G28="","",Barras!G28*(1+TaxaCompra)) | J28: =IF(Barras!H28="","",Barras!H28) | K28: Automático | L28: =IF(K28="Comprar",I28,IF(K28="Refinar",H28,IF(AND(H28="",I28=""),"",IF(H28="",I28,IF(I28="",H28,MIN(H28,I28)))))) | M28: =IF(L28="","",IF(K28="Comprar","Comprar",IF(K28="Refinar","Refinar",IF(H28="","Comprar",IF(I28="","Refinar",IF(H28<=I28,"Refinar","Comprar")))))) | N28: =SUMIF(Craft!$C$6:$C$35,$A28,Craft!$S$6:$S$35) | O28: 0 | P28: =N28+O28 | Q28: =IF(M28="Comprar",P28,0) | R28: =IF(M28="Refinar",P28,0) | S28: =R28*E28*(1-RetRefino) | T28: =IF(AND(Q28>0,ISNUMBER(I28)),Q28*I28,0) | U28: =IF(AND(S28>0,ISNUMBER(G28)),S28*G28,0) | V28: =IF(Minerio!H28="","",Minerio!H28)
A29: T8.4 | B29: 8 | C29: 4 | D29: =2^B29*2^C29 | E29: 5 | F29: T7.4 | G29: =IF(Minerio!G29="","",Minerio!G29*(1+TaxaCompra)) | H29: =IF(OR(G29="",L24=""),"",(E29*G29+L24)*(1-RetRefino)+D29*0.1125*FeeRefino/100) | I29: =IF(Barras!G29="","",Barras!G29*(1+TaxaCompra)) | J29: =IF(Barras!H29="","",Barras!H29) | K29: Automático | L29: =IF(K29="Comprar",I29,IF(K29="Refinar",H29,IF(AND(H29="",I29=""),"",IF(H29="",I29,IF(I29="",H29,MIN(H29,I29)))))) | M29: =IF(L29="","",IF(K29="Comprar","Comprar",IF(K29="Refinar","Refinar",IF(H29="","Comprar",IF(I29="","Refinar",IF(H29<=I29,"Refinar","Comprar")))))) | N29: =SUMIF(Craft!$C$6:$C$35,$A29,Craft!$S$6:$S$35) | O29: 0 | P29: =N29+O29 | Q29: =IF(M29="Comprar",P29,0) | R29: =IF(M29="Refinar",P29,0) | S29: =R29*E29*(1-RetRefino) | T29: =IF(AND(Q29>0,ISNUMBER(I29)),Q29*I29,0) | U29: =IF(AND(S29>0,ISNUMBER(G29)),S29*G29,0) | V29: =IF(Minerio!H29="","",Minerio!H29)

Sheet Minerio
A1: Preço de compra do minério bruto (Iron Ore etc.)
A2: Tier | B2: Thetford | C2: Martlock | D2: Bridgewatch | E2: Lymhurst | F2: Fort Sterling | G2: Menor preço | H2: Cidade mais barata
A3: T2.0 | G3: =IF(COUNT(B3:F3)=0,"",MIN(B3:F3)) | H3: =IF(G3="","",INDEX($B$2:$F$2,MATCH(G3,B3:F3,0)))
A4: T3.0 | G4: =IF(COUNT(B4:F4)=0,"",MIN(B4:F4)) | H4: =IF(G4="","",INDEX($B$2:$F$2,MATCH(G4,B4:F4,0)))
A5: T4.0 | B5: 155 | C5: 120 | D5: 350 | E5: 144 | F5: 140 | G5: =IF(COUNT(B5:F5)=0,"",MIN(B5:F5)) | H5: =IF(G5="","",INDEX($B$2:$F$2,MATCH(G5,B5:F5,0)))
A6: T4.1 | B6: 198 | C6: 270 | D6: 968 | E6: 188 | F6: 216 | G6: =IF(COUNT(B6:F6)=0,"",MIN(B6:F6)) | H6: =IF(G6="","",INDEX($B$2:$F$2,MATCH(G6,B6:F6,0)))
A7: T4.2 | B7: 830 | C7: 858 | E7: 1041 | F7: 894 | G7: =IF(COUNT(B7:F7)=0,"",MIN(B7:F7)) | H7: =IF(G7="","",INDEX($B$2:$F$2,MATCH(G7,B7:F7,0)))
A8: T4.3 | G8: =IF(COUNT(B8:F8)=0,"",MIN(B8:F8)) | H8: =IF(G8="","",INDEX($B$2:$F$2,MATCH(G8,B8:F8,0)))
A9: T4.4 | G9: =IF(COUNT(B9:F9)=0,"",MIN(B9:F9)) | H9: =IF(G9="","",INDEX($B$2:$F$2,MATCH(G9,B9:F9,0)))
A10: T5.0 | C10: 300 | D10: 498 | E10: 595 | F10: 389 | G10: =IF(COUNT(B10:F10)=0,"",MIN(B10:F10)) | H10: =IF(G10="","",INDEX($B$2:$F$2,MATCH(G10,B10:F10,0)))
A11: T5.1 | C11: 563 | D11: 588 | E11: 611 | F11: 597 | G11: =IF(COUNT(B11:F11)=0,"",MIN(B11:F11)) | H11: =IF(G11="","",INDEX($B$2:$F$2,MATCH(G11,B11:F11,0)))
A12: T5.2 | B12: 1679 | C12: 1883 | F12: 3788 | G12: =IF(COUNT(B12:F12)=0,"",MIN(B12:F12)) | H12: =IF(G12="","",INDEX($B$2:$F$2,MATCH(G12,B12:F12,0)))
A13: T5.3 | G13: =IF(COUNT(B13:F13)=0,"",MIN(B13:F13)) | H13: =IF(G13="","",INDEX($B$2:$F$2,MATCH(G13,B13:F13,0)))
A14: T5.4 | G14: =IF(COUNT(B14:F14)=0,"",MIN(B14:F14)) | H14: =IF(G14="","",INDEX($B$2:$F$2,MATCH(G14,B14:F14,0)))
A15: T6.0 | G15: =IF(COUNT(B15:F15)=0,"",MIN(B15:F15)) | H15: =IF(G15="","",INDEX($B$2:$F$2,MATCH(G15,B15:F15,0)))
A16: T6.1 | G16: =IF(COUNT(B16:F16)=0,"",MIN(B16:F16)) | H16: =IF(G16="","",INDEX($B$2:$F$2,MATCH(G16,B16:F16,0)))
A17: T6.2 | G17: =IF(COUNT(B17:F17)=0,"",MIN(B17:F17)) | H17: =IF(G17="","",INDEX($B$2:$F$2,MATCH(G17,B17:F17,0)))
A18: T6.3 | G18: =IF(COUNT(B18:F18)=0,"",MIN(B18:F18)) | H18: =IF(G18="","",INDEX($B$2:$F$2,MATCH(G18,B18:F18,0)))
A19: T6.4 | G19: =IF(COUNT(B19:F19)=0,"",MIN(B19:F19)) | H19: =IF(G19="","",INDEX($B$2:$F$2,MATCH(G19,B19:F19,0)))
A20: T7.0 | G20: =IF(COUNT(B20:F20)=0,"",MIN(B20:F20)) | H20: =IF(G20="","",INDEX($B$2:$F$2,MATCH(G20,B20:F20,0)))
A21: T7.1 | G21: =IF(COUNT(B21:F21)=0,"",MIN(B21:F21)) | H21: =IF(G21="","",INDEX($B$2:$F$2,MATCH(G21,B21:F21,0)))
A22: T7.2 | G22: =IF(COUNT(B22:F22)=0,"",MIN(B22:F22)) | H22: =IF(G22="","",INDEX($B$2:$F$2,MATCH(G22,B22:F22,0)))
A23: T7.3 | G23: =IF(COUNT(B23:F23)=0,"",MIN(B23:F23)) | H23: =IF(G23="","",INDEX($B$2:$F$2,MATCH(G23,B23:F23,0)))
A24: T7.4 | G24: =IF(COUNT(B24:F24)=0,"",MIN(B24:F24)) | H24: =IF(G24="","",INDEX($B$2:$F$2,MATCH(G24,B24:F24,0)))
... A29: T8.4 | G29: =IF(COUNT(B29:F29)=0,"",MIN(B29:F29)) | H29: =IF(G29="","",INDEX($B$2:$F$2,MATCH(G29,B29:F29,0)))

Sheet Barras
A1: Preço de compra das barras de metal prontas (Metal Bar)
A2: Tier | B2: Thetford | C2: Martlock | D2: Bridgewatch | E2: Lymhurst | F2: Fort Sterling | G2: Menor preço | H2: Cidade mais barata
A3: T2.0 | G3: =IF(COUNT(B3:F3)=0,"",MIN(B3:F3)) | H3: =IF(G3="","",INDEX($B$2:$F$2,MATCH(G3,B3:F3,0)))
A4: T3.0 | B4: 232 | C4: 253 | D4: 246 | E4: 207 | F4: 207 | G4: =IF(COUNT(B4:F4)=0,"",MIN(B4:F4)) | H4: =IF(G4="","",INDEX($B$2:$F$2,MATCH(G4,B4:F4,0)))
A5: T4.0 | B5: 275 | C5: 322 | D5: 384 | E5: 285 | F5: 237 | G5: =IF(COUNT(B5:F5)=0,"",MIN(B5:F5)) | H5: =IF(G5="","",INDEX($B$2:$F$2,MATCH(G5,B5:F5,0)))
A6: T4.1 | B6: 347 | C6: 382 | D6: 407 | E6: 360 | F6: 380 | G6: =IF(COUNT(B6:F6)=0,"",MIN(B6:F6)) | H6: =IF(G6="","",INDEX($B$2:$F$2,MATCH(G6,B6:F6,0)))
A7: T4.2 | B7: 1449 | C7: 1627 | E7: 1336 | F7: 1461 | G7: =IF(COUNT(B7:F7)=0,"",MIN(B7:F7)) | H7: =IF(G7="","",INDEX($B$2:$F$2,MATCH(G7,B7:F7,0)))
A8: T4.3 | G8: =IF(COUNT(B8:F8)=0,"",MIN(B8:F8)) | H8: =IF(G8="","",INDEX($B$2:$F$2,MATCH(G8,B8:F8,0)))
A9: T4.4 | G9: =IF(COUNT(B9:F9)=0,"",MIN(B9:F9)) | H9: =IF(G9="","",INDEX($B$2:$F$2,MATCH(G9,B9:F9,0)))
A10: T5.0 | G10: =IF(COUNT(B10:F10)=0,"",MIN(B10:F10)) | H10: =IF(G10="","",INDEX($B$2:$F$2,MATCH(G10,B10:F10,0)))
A11: T5.1 | G11: =IF(COUNT(B11:F11)=0,"",MIN(B11:F11)) | H11: =IF(G11="","",INDEX($B$2:$F$2,MATCH(G11,B11:F11,0)))
A12: T5.2 | G12: =IF(COUNT(B12:F12)=0,"",MIN(B12:F12)) | H12: =IF(G12="","",INDEX($B$2:$F$2,MATCH(G12,B12:F12,0)))
A13: T5.3 | G13: =IF(COUNT(B13:F13)=0,"",MIN(B13:F13)) | H13: =IF(G13="","",INDEX($B$2:$F$2,MATCH(G13,B13:F13,0)))
A14: T5.4 | G14: =IF(COUNT(B14:F14)=0,"",MIN(B14:F14)) | H14: =IF(G14="","",INDEX($B$2:$F$2,MATCH(G14,B14:F14,0)))
A15: T6.0 | G15: =IF(COUNT(B15:F15)=0,"",MIN(B15:F15)) | H15: =IF(G15="","",INDEX($B$2:$F$2,MATCH(G15,B15:F15,0)))
A16: T6.1 | G16: =IF(COUNT(B16:F16)=0,"",MIN(B16:F16)) | H16: =IF(G16="","",INDEX($B$2:$F$2,MATCH(G16,B16:F16,0)))
A17: T6.2 | G17: =IF(COUNT(B17:F17)=0,"",MIN(B17:F17)) | H17: =IF(G17="","",INDEX($B$2:$F$2,MATCH(G17,B17:F17,0)))
A18: T6.3 | G18: =IF(COUNT(B18:F18)=0,"",MIN(B18:F18)) | H18: =IF(G18="","",INDEX($B$2:$F$2,MATCH(G18,B18:F18,0)))
A19: T6.4 | G19: =IF(COUNT(B19:F19)=0,"",MIN(B19:F19)) | H19: =IF(G19="","",INDEX($B$2:$F$2,MATCH(G19,B19:F19,0)))
... A29: T8.4 | G29: =IF(COUNT(B29:F29)=0,"",MIN(B29:F29)) | H29: =IF(G29="","",INDEX($B$2:$F$2,MATCH(G29,B29:F29,0)))

Sheet Artefatos
A1: Preço de compra dos artefatos (1 por peça craftada - não retorna no craft)
A2: Chave | B2: Variante | C2: Peça | D2: Tier | E2: Artefato | F2: Valor do item | G2: Thetford | H2: Martlock | I2: Bridgewatch | J2: Lymhurst | K2: Fort Sterling | L2: Menor preço | M2: Cidade mais barata
A3: Graveguard|Armadura|T4 | B3: Graveguard | C3: Armadura | D3: T4 | E3: Ancient Chain Rings | F3: 64 | L3: =IF(COUNT(G3:K3)=0,"",MIN(G3:K3)) | M3: =IF(L3="","",INDEX($G$2:$K$2,MATCH(L3,G3:K3,0)))
A4: Graveguard|Armadura|T5 | B4: Graveguard | C4: Armadura | D4: T5 | E4: Ancient Chain Rings | F4: 128 | L4: =IF(COUNT(G4:K4)=0,"",MIN(G4:K4)) | M4: =IF(L4="","",INDEX($G$2:$K$2,MATCH(L4,G4:K4,0)))
A5: Graveguard|Armadura|T6 | B5: Graveguard | C5: Armadura | D5: T6 | E5: Ancient Chain Rings | F5: 256 | L5: =IF(COUNT(G5:K5)=0,"",MIN(G5:K5)) | M5: =IF(L5="","",INDEX($G$2:$K$2,MATCH(L5,G5:K5,0)))
A6: Graveguard|Armadura|T7 | B6: Graveguard | C6: Armadura | D6: T7 | E6: Ancient Chain Rings | F6: 512 | L6: =IF(COUNT(G6:K6)=0,"",MIN(G6:K6)) | M6: =IF(L6="","",INDEX($G$2:$K$2,MATCH(L6,G6:K6,0)))
A7: Graveguard|Armadura|T8 | B7: Graveguard | C7: Armadura | D7: T8 | E7: Ancient Chain Rings | F7: 1024 | L7: =IF(COUNT(G7:K7)=0,"",MIN(G7:K7)) | M7: =IF(L7="","",INDEX($G$2:$K$2,MATCH(L7,G7:K7,0)))
A8: Graveguard|Elmo|T4 | B8: Graveguard | C8: Elmo | D8: T4 | E8: Ancient Padding | F8: 32 | L8: =IF(COUNT(G8:K8)=0,"",MIN(G8:K8)) | M8: =IF(L8="","",INDEX($G$2:$K$2,MATCH(L8,G8:K8,0)))
A9: Graveguard|Elmo|T5 | B9: Graveguard | C9: Elmo | D9: T5 | E9: Ancient Padding | F9: 64 | L9: =IF(COUNT(G9:K9)=0,"",MIN(G9:K9)) | M9: =IF(L9="","",INDEX($G$2:$K$2,MATCH(L9,G9:K9,0)))
A10: Graveguard|Elmo|T6 | B10: Graveguard | C10: Elmo | D10: T6 | E10: Ancient Padding | F10: 128 | L10: =IF(COUNT(G10:K10)=0,"",MIN(G10:K10)) | M10: =IF(L10="","",INDEX($G$2:$K$2,MATCH(L10,G10:K10,0)))
A11: Graveguard|Elmo|T7 | B11: Graveguard | C11: Elmo | D11: T7 | E11: Ancient Padding | F11: 256 | L11: =IF(COUNT(G11:K11)=0,"",MIN(G11:K11)) | M11: =IF(L11="","",INDEX($G$2:$K$2,MATCH(L11,G11:K11,0)))
A12: Graveguard|Elmo|T8 | B12: Graveguard | C12: Elmo | D12: T8 | E12: Ancient Padding | F12: 512 | L12: =IF(COUNT(G12:K12)=0,"",MIN(G12:K12)) | M12: =IF(L12="","",INDEX($G$2:$K$2,MATCH(L12,G12:K12,0)))
A13: Graveguard|Botas|T4 | B13: Graveguard | C13: Botas | D13: T4 | E13: Ancient Bindings | F13: 32 | L13: =IF(COUNT(G13:K13)=0,"",MIN(G13:K13)) | M13: =IF(L13="","",INDEX($G$2:$K$2,MATCH(L13,G13:K13,0)))
A14: Graveguard|Botas|T5 | B14: Graveguard | C14: Botas | D14: T5 | E14: Ancient Bindings | F14: 64 | L14: =IF(COUNT(G14:K14)=0,"",MIN(G14:K14)) | M14: =IF(L14="","",INDEX($G$2:$K$2,MATCH(L14,G14:K14,0)))
... A77: Valor|Botas|T8 | B77: Valor | C77: Botas | D77: T8 | E77: Exalted Greave | F77: 7680 | L77: =IF(COUNT(G77:K77)=0,"",MIN(G77:K77)) | M77: =IF(L77="","",INDEX($G$2:$K$2,MATCH(L77,G77:K77,0)))

Sheet Listas
A1: Variante | C1: Peça | E1: Tier
A2: Soldado (Soldier) | C2: Armadura | E2: T4.0
A3: Cavaleiro (Knight) | C3: Elmo | E3: T4.1
A4: Guardião (Guardian) | C4: Botas | E4: T4.2
A5: Graveguard | E5: T4.3
A6: Demônio (Demon) | E6: T4.4
A7: Juiz (Judicator) | E7: T5.0
A8: Duskweaver | E8: T5.1
A9: Valor | E9: T5.2
E10: T5.3
E11: T5.4
E12: T6.0
E13: T6.1
E14: T6.2
E15: T6.3
E16: T6.4
E17: T7.0
E18: T7.1
E19: T7.2
E20: T7.3
E21: T7.4
... E26: T8.4
