Workbook

Sheet Config e Taxas
A1: Parâmetro | B1: Valor | C1: Descrição
A2: Taxa de Ordem de Compra | B2: 0.025 | C2: Taxa cobrada ao criar Buy Orders (2,5%)
A3: Taxa de Venda (Mercado) | B3: 0.065 | C3: Taxa cobrada na venda (6,5% com Premium, 10,5% sem)
A4: Retorno Refino (Sinergia) | B4: 0.367 | C4: Taxa de retorno ao refinar (Ex: 36,7% em cidade com bônus)
A5: Retorno Craft (Sinergia) | B5: 0.248 | C5: Taxa de retorno ao craftar o item (Ex: 24,8% com bônus)
A6: Taxa Barraca Refino | B6: 500 | C6: Prata por 100 de nutrição na Fundição
A7: Taxa Barraca Craft | B7: 500 | C7: Prata por 100 de nutrição na Forja de Armaduras

Sheet Refino (Barras)
A1: Tier da Barra | B1: Preço Minério (Mercado) | C1: Preço Barra T-1 (Puxa Auto) | D1: Item Value (IV) | E1: Custo Minério Bruto | F1: Custo Barra Antiga | G1: Custo Barraca | H1: Custo Unitário Real (Integrado)
A2: T3.0 | B2: 35 | C2: 15 | D2: 6 | E2: =2*B2*(1+'Config e Taxas'!$B$2) | F2: =1*C2 | G2: =D2*0.1125*('Config e Taxas'!$B$6/100) | H2: =(E2+F2+G2)*(1-'Config e Taxas'!$B$4)
A3: T4.0 | B3: 120 | C3: =H2 | D3: 16 | E3: =2*B3*(1+'Config e Taxas'!$B$2) | F3: =1*C3 | G3: =D3*0.1125*('Config e Taxas'!$B$6/100) | H3: =(E3+F3+G3)*(1-'Config e Taxas'!$B$4)
A4: T4.1 | B4: 200 | C4: =H2 | D4: 32 | E4: =2*B4*(1+'Config e Taxas'!$B$2) | F4: =1*C4 | G4: =D4*0.1125*('Config e Taxas'!$B$6/100) | H4: =(E4+F4+G4)*(1-'Config e Taxas'!$B$4)
A5: T4.2 | B5: 800 | C5: =H2 | D5: 64 | E5: =2*B5*(1+'Config e Taxas'!$B$2) | F5: =1*C5 | G5: =D5*0.1125*('Config e Taxas'!$B$6/100) | H5: =(E5+F5+G5)*(1-'Config e Taxas'!$B$4)
A6: T5.0 | B6: 300 | C6: =H3 | D6: 30 | E6: =3*B6*(1+'Config e Taxas'!$B$2) | F6: =1*C6 | G6: =D6*0.1125*('Config e Taxas'!$B$6/100) | H6: =(E6+F6+G6)*(1-'Config e Taxas'!$B$4)

Sheet Craft (Equip de Placas)
A1: Item | B1: Tier | C1: Qtd Barras | D1: Custo Barra (Refino) | E1: Item Value (IV) | F1: Custo Base Material | G1: Economia do Retorno | H1: Taxa do Ferreiro | I1: CUSTO TOTAL DO ITEM | J1: Preço Venda (Mercado) | K1: Taxa de Venda | L1: LUCRO REAL | M1: Margem (%)
A2: Armadura de Placas | B2: T4.0 | C2: 16 | D2: ='Refino (Barras)'!H3 | E2: 256 | F2: =C2*D2 | G2: =F2*'Config e Taxas'!$B$5 | H2: =E2*0.1125*('Config e Taxas'!$B$7/100) | I2: =F2-G2+H2 | J2: 15000 | K2: =J2*'Config e Taxas'!$B$3 | L2: =J2-K2-I2 | M2: =L2/I2
A3: Elmo de Placas | B3: T4.0 | C3: 8 | D3: ='Refino (Barras)'!H3 | E3: 128 | F3: =C3*D3 | G3: =F3*'Config e Taxas'!$B$5 | H3: =E3*0.1125*('Config e Taxas'!$B$7/100) | I3: =F3-G3+H3 | J3: 8000 | K3: =J3*'Config e Taxas'!$B$3 | L3: =J3-K3-I3 | M3: =L3/I3
A4: Botas de Placas | B4: T4.0 | C4: 8 | D4: ='Refino (Barras)'!H3 | E4: 128 | F4: =C4*D4 | G4: =F4*'Config e Taxas'!$B$5 | H4: =E4*0.1125*('Config e Taxas'!$B$7/100) | I4: =F4-G4+H4 | J4: 8000 | K4: =J4*'Config e Taxas'!$B$3 | L4: =J4-K4-I4 | M4: =L4/I4
A5: Armadura de Placas | B5: T4.1 | C5: 16 | D5: ='Refino (Barras)'!H4 | E5: 512 | F5: =C5*D5 | G5: =F5*'Config e Taxas'!$B$5 | H5: =E5*0.1125*('Config e Taxas'!$B$7/100) | I5: =F5-G5+H5 | J5: 35000 | K5: =J5*'Config e Taxas'!$B$3 | L5: =J5-K5-I5 | M5: =L5/I5
A6: Armadura de Placas | B6: T5.0 | C6: 16 | D6: ='Refino (Barras)'!H6 | E6: 512 | F6: =C6*D6 | G6: =F6*'Config e Taxas'!$B$5 | H6: =E6*0.1125*('Config e Taxas'!$B$7/100) | I6: =F6-G6+H6 | J6: 25000 | K6: =J6*'Config e Taxas'!$B$3 | L6: =J6-K6-I6 | M6: =L6/I6
